Workbook
Name Periodicity: 'Model Inputs'!$E$7

Sheet Notes

Sheet Cover
B2: Formatting Conventions
D4: Input | E4: 1000 | F4: Fundamental model inputs / assumptions, hardcoded value
D6: Technical Input | E6: 1000 | F6: Input values that determine model integrity / structure and should not be changed
D8: Calculation | E8: 1000 | F8: Stand-alone calculation or reference within sheet
D10: Linked | E10: 1000 | F10: Reference to a different sheet
D12: Sensitivity | E12: 1000 | F12: Input cell linked to sensivity analysis
D14: Blank | F14: Cell left intentionally blank for a functional purpose, may have dependents
D16: Explanatory | E16: ABC | F16: Contextual support
D18: Note | E18: ABC | F18: Additional information

Sheet Project Inputs
B2: LAND
C4: Details
D5: Model | E5: =Output!E9 -> Operating Lease | F5: "Ownership" covers both freehold and pre-paid ground lease
D6: Land Area | E6: 49109 | F6: sqm
C8: Value | E8: Per sqm | F8: Total
D9: Value (excl GST) | E9: 150 | F9: =Output!E12*$E$6 -> 9821800
D10: Value (incl GST) | E10: =Output!E12*1.15 -> 230 | F10: =E10*$E$6 -> 11295070
C12: Lease
D13: Cap Rate | E13: 0.06 | F13: applied to the GST inclusive land value
D14: Rental - annual (incl GST) | E14: =Output!E15*F10 -> 677704.2
D15: Rental - period (incl GST) | E15: =E14/Periodicity -> 56475.35
B18: DEVELOPMENT OVERVIEW
D20: Unit Type | E20: Description | F20: Typology | G20: Bedrooms | H20: Bathrooms | I20: Garages | J20: Floor Area | K20: Value Ratio | L20: Market Value | M20: Quantity | N20: Value Ratio Reworked | O20: Value per SQm | P20: Sales lag
D21: KDG | E21: Standalone | F21: House | G21: 3 | H21: 2 | I21: 2 | J21: 180 | K21: 1.25 | L21: =$E$41*N21 -> 1384943.2 | M21: 0 | N21: =K21/88%*100% -> 1.4204545
D22: HDG | E22: Standalone | F22: House | G22: 3 | H22: 2 | I22: 2 | J22: 180 | K22: 1.02 | L22: =$E$42*N22 -> 1275000 | M22: 0 | N22: =K22/88%*100% -> 1.1590909
D23: NDG | E23: Standalone | F23: House | G23: 3 | H23: 2 | I23: 2 | J23: 180 | K23: 1 | L23: =$E$42*N23 -> 1250000 | M23: 0 | N23: =K23/88%*100% -> 1.1363636
D24: BSG | E24: 2 bed duplex | F24: House | G24: 2 | H24: 1.5 | I24: 1 | J24: 121.6 | K24: 0.78 | L24: =$E$41*N24 -> 975000 | M24: 53 | N24: 1 | O24: =L24/J24 -> 8018.0921
D25: JMSG | E25: 2 bed duplex | F25: House | G25: 2 | H25: 1.5 | I25: 1 | J25: 120.9 | K25: 0.77 | L25: =$E$41*N25 -> 962500 | M25: 0 | N25: =K25/78%*100% -> 0.98717949
D26: JMDG | E26: 2 bed duplex | F26: House | G26: 2 | H26: 1.5 | I26: 2 | J26: 137.1 | K26: 0.8 | L26: =$E$41*N26 -> 1000000 | M26: 0 | N26: =K26/78%*100% -> 1.025641
D27: ESG | E27: 3 bed duplex | F27: House | G27: 3 | H27: 2 | I27: 1 | J27: 133.4 | K27: 0.885 | L27: =$E$42*N27 -> 1106250 | M27: 0 | N27: =K27/88%*100% -> 1.0056818
D28: MSG | E28: 3 bed duplex | F28: House | G28: 3 | H28: 2 | I28: 1 | J28: 139.33 | K28: 0.887 | L28: =$E$42*N28 -> 1108750 | M28: 0 | N28: =K28/88%*100% -> 1.0079545
D29: MNSG | E29: 3bd (mix dpl and stand) | F29: House | G29: 3 | H29: 2 | I29: 1 | J29: 144.2 | K29: 0.88 | L29: =$E$42*N29 -> 1100000 | M29: 32 | N29: 1 | O29: =L29/J29 -> 7628.294
D30: LSG | E30: 3 bed duplex | F30: House | G30: 3 | H30: 2 | I30: 1 | J30: 145.67 | K30: 0.88 | L30: =$E$42*N30 -> 1100000 | M30: 0 | N30: =K30/88%*100% -> 1
D31: MDG | E31: 3 bed duplex | F31: House | G31: 3 | H31: 2 | I31: 2 | J31: 155.58 | K31: 0.96 | L31: =$E$42*N31 -> 1200000 | M31: 0 | N31: =K31/88%*100% -> 1.0909091
D32: R6 | E32: 1 bed dplx | F32: House | G32: 1 | H32: 1 | I32: 1 | J32: 90 | K32: 0.65 | L32: =$E$41*N32 -> 812500 | M32: 20 | N32: =K32/78%*100% -> 0.83333333 | O32: =L32/J32 -> 9027.7778
D33: S1 | E33: Stanaway | F33: Apartment | G33: 2 | H33: 2 | I33: 1 | J33: 148.69605 | K33: 0.86 | L33: =$E$41*N33 -> 1075000 | M33: 0 | N33: =K33/78%*100% -> 1.1025641
D34: S2 | E34: Stanaway | F34: Apartment | G34: 2 | H34: 2 | I34: 1 | J34: 139.60596 | K34: 0.86 | L34: =$E$41*N34 -> 1075000 | M34: 0 | N34: =K34/78%*100% -> 1.1025641
D35: S3 | E35: Stanaway | F35: Apartment | G35: 2 | H35: 2 | I35: 1 | J35: 152.21767 | K35: 0.92 | L35: =$E$41*N35 -> 1150000 | M35: 0 | N35: =K35/78%*100% -> 1.1794872
D36: S4 | E36: Stanaway | F36: Apartment | G36: 3.5 | H36: 2 | I36: 1 | J36: 238.78328 | K36: 0.89 | L36: 0 | M36: 0 | N36: N/A
D37: S5 | E37: Stanaway | F37: Apartment | G37: 2.5 | H37: 2 | I37: 1 | J37: 198.64704 | K37: 0.92 | L37: 0 | M37: 0 | N37: N/A
D38: Total / Weighted Average | L38: =SUMPRODUCT(L21:L37,M21:M37)/M38 -> 982142.86 | M38: =SUM(M21:M37) -> 105
D40: Base Value 1 Bedroom Units | E40: =L32 -> 812500
D41: Base Value 2 Bedroom Units (base) | E41: 975000 | L41: updated - need to confimr pricing
D42: Base Value 3 Bedroom Units | E42: 1100000
B44: VERTICAL CONSTRUCTION
D46: Input Build Rate (psm) (incl GST) | E46: ='House Build Up'!C8 -> 3718.6475 | J46: Proposed starting uint pricing
D47: Sensitivity | E47: 0
D48: Applied Build Rate (psm) (incl GST) | E48: =E46*(1+E47) -> 3718.6475
D49: Apartment Premium | E49: 0.4
C51: Costs
E52: ='Model Inputs'!E74 -> House | F52: ='Model Inputs'!F74 -> Apartment | G52: Total
D53: Build Rate (psm) (incl GST) | E53: =E48 -> 3718.6475 | F53: =E48*(1+E49) -> 5206.1066 | G53: =SUMPRODUCT(E53:F53,E54:F54)/SUM(E54:F54) -> 3718.6475
D54: Floor Area | E54: {=SUM(($F$21:$F$37=E$52)*($J$21:$J$37)*($M$21:$M$37))} -> 12859.2 | F54: {=SUM(($F$21:$F$37=F$52)*($J$21:$J$37)*($M$21:$M$37))} -> 0 | G54: =SUM(E54:F54) -> 12859.2
D55: Total Cost (incl GST) | E55: =E53*E54 -> 47818832 | F55: =F53*F54 -> 0 | G55: =G53*G54 -> 47818832
B58: LAND DEVELOPMENT
C60: Costs
E61: Base | G61: Rate (excl GST) | H61: Total (excl GST) | I61: Total (incl GST)
D62: P&G per stage | E62: 3 | G62: 55000 | H62: =E62*G62 -> 165000 | I62: =H62*1.15 -> 189750
D63: Landscaping | E63: =$M$38 -> 105 | F63: units | G63: 20000 | H63: =E63*G63 -> 2100000 | I63: =H63*1.15 -> 2415000
D64: Signage and Entrance | E64: 1 | G64: 40000 | H64: =E64*G64 -> 40000 | I64: =H64*1.15 -> 46000
D65: Fencing frontage | E65: 275 | G65: 400 | H65: =E65*G65 -> 110000 | I65: =H65*1.15 -> 126500
D66: Fencing back | E66: 175 | G66: 400 | H66: =E66*G66 -> 70000 | I66: =H66*1.15 -> 80500
D67: Roading Internal | E67: =$M$38 -> 105 | F67: units | G67: 11000 | H67: =E67*G67 -> 1155000 | I67: =H67*1.15 -> 1328250
D68: Sewer | E68: =$M$38 -> 105 | F68: units | G68: 4500 | H68: =E68*G68 -> 472500 | I68: =H68*1.15 -> 543375 | K68: average across standard villages is 120k
D69: Stormwater | E69: =$M$38 -> 105 | F69: units | G69: 6100 | H69: =E69*G69 -> 640500 | I69: =H69*1.15 -> 736575 | K69: Waihi beach with stormwater/high DC's is ~220k
D70: Water Mains reticulation | E70: =$M$38 -> 105 | F70: units | G70: 3500 | H70: =E70*G70 -> 367500 | I70: =H70*1.15 -> 422625
D71: Earthworks & land remediation | E71: 91 | F71: units | G71: 45000 | H71: =E71*G71 -> 4095000 | I71: =H71*1.15 -> 4709250
D72: Additional earthworks to foreshore | E72: 10000 | G72: 20 | H72: =E72*G72 -> 200000 | I72: =H72*1.15 -> 230000
D73: Clearance & sediment control | E73: =$E$6 -> 49109 | F73: sqm | G73: 4 | H73: =E73*G73 -> 196436 | I73: =H73*1.15 -> 225901.4
D74: Sloping land retaining walls | E74: 12000 | G74: 30 | H74: =E74*G74 -> 360000 | I74: =H74*1.15 -> 414000
D75: Power | E75: =$M$38 -> 105 | F75: units | G75: 8000 | H75: =E75*G75 -> 840000 | I75: =H75*1.15 -> 966000
D76: Streetlights | E76: =$M$38/2 -> 52.5 | F76: units / 2 | G76: 3500 | H76: =E76*G76 -> 183750 | I76: =H76*1.15 -> 211312.5
D77: Fibre | E77: =$M$38 -> 105 | F77: units | G77: 500 | H77: =E77*G77 -> 52500 | I77: =H77*1.15 -> 60375
D78: Nursecall/Security System | E78: =$M$38 -> 105 | F78: units | G78: 4500 | H78: =E78*G78 -> 472500 | I78: =H78*1.15 -> 543375
D79: Total | H79: =SUM(H62:H78) -> 11520686 | I79: =SUM(I62:I78) -> 13248789
I80: =I79/M38 -> 126178.94
B82: COMMUNITY CENTRE
C84: Residents
D85: Units | E85: =M38 -> 105
D86: Average residents per unit | E86: 1.7
D87: Total residents (estimate) | E87: =E85*E86 -> 178.5
C89: Community Centre Components
E90: Area Required
D91: Hospital | E91: 0 | F91: n/a
D92: Dining room | E92: =2*E87 -> 357 | F92: 2sqm per resident
D93: Kitchen | E93: =E85/50*20 -> 42 | F93: 20sqm per x50 units
D94: Toilets | E94: =E87/10*4 -> 71.4 | F94: 4sqm per x10 residentsunits
D95: Games | E95: =E85/50*35 -> 73.5 | F95: 35sqm per x50 units
D96: Changing & Shower | E96: =E85/50*20 -> 42 | F96: 20sqm per x50 units
D97: Gym | E97: =E96*0.3 -> 12.6 | F97: 30% of gym
D98: Pool area | E98: 200 | F98: hardcode
D99: Admin and Staff area | E99: 50 | F99: hardcode
D100: Total | E100: =SUM(E91:E99) -> 848.5
C102: Village Rating
D103: Village Star Rating | E103: 4.5
D105: Rating | E105: Garden area | F105: Garden Costs | G105: Pavilion cost | H105: Fit out cost
D106: 4.5 | E106: 24 | F106: 250 | G106: 7000 | H106: 800
D107: 4 | E107: 22 | F107: 235 | G107: 6000 | H107: 667
D108: 3.5 | E108: 20 | F108: 217 | G108: 5000 | H108: 533
D109: 3 | E109: 18 | F109: 200 | G109: 4000 | H109: 400
C111: Costs
E112: Base | G112: Rate (incl GST) | H112: Total (incl GST)
D113: Pavilion Cost | E113: =E100 -> 848.5 | F113: sqm | G113: 5000 | H113: =E113*G113 -> 4242500
D114: Pavilion Design | E114: =H113 -> 4242500 | G114: 0.1 | H114: =E114*G114 -> 424250
D115: Fit out cost | E115: =E100 -> 848.5 | F115: sqm | G115: 1500 | H115: =E115*G115 -> 1272750
D116: Visitor parking | E116: =E87/10 -> 17.85 | F116: 1 per 10 residents | G116: 3705 | H116: =E116*G116 -> 66134.25
D117: Communal Gardens | E117: {=SUM(($D$106:$D$109=$E$103)*$E$106:$E$109)*E85} -> 2520 | G117: {=SUM(($D$106:$D$109=$E$103)*$F$106:$F$109)} -> 250 | H117: =E117*G117 -> 630000
D118: Breathing spaces | E118: 0 | G118: 0 | H118: =E118*G118 -> 0
D119: Bowling green | E119: 5 | F119: lanes | G119: 60000 | H119: =E119*G119 -> 300000
D120: Swimming Pool | E120: 0 | G120: 0 | H120: =E120*G120 -> 0
...

Sheet Model Inputs
B2: GENERAL
D4: Model Commencement Date | E4: 46203 | F4: placeholder for XIRR
D6: Model Term | E6: 15 | F6: years
D7: Periodicity | E7: 12 | F7: 1 = annually; 2 = biannually; 4 = quarterly; 12 = monthly
B10: STRUCTURE
C12: Share Class Structure
D13: A Class | E13: 0.7
D14: B Class | E14: 0.3
C16: A Class Share Allocation
D17: Hāpai | E17: 1
D18: Vendor | E18: 0
C20: B Class Share Allocation
D21: Hāpai | E21: 0.5
D22: KPV | E22: 0.5
C24: Shareholdings
E25: Hāpai | F25: KPV | G25: =D18 -> Vendor | H25: Total
D26: A-Class | E26: =E13*E17 -> 0.7 | F26: 0 | G26: =E13*E18 -> 0 | H26: =SUM(E26:G26) -> 0.7
D27: B-Class | E27: =E21*E14 -> 0.15 | F27: =E22*E14 -> 0.15 | G27: 0 | H27: =SUM(E27:G27) -> 0.3
D28: Total | E28: =SUM(E26:E27) -> 0.85 | F28: =SUM(F26:F27) -> 0.15 | G28: =SUM(G26:G27) -> 0 | H28: =SUM(H26:H27) -> 1
C30: Preferred Interest (A-Class)
D31: Paid | E31: 0.045 | G31: Funder Choice - need spend on the opex
D32: Accrued | E32: 0.035
D33: Total | E33: =SUM(E31:E32) -> 0.08
B36: OPERATING
C38: Unit Turnover
D39: Average Resident Tenure | E39: 8 | F39: years | G39: 2 stages | H39: development | I39: longer | J39: 10-12
D40: Average DMF | E40: 0.24 | H40: steady state | J40: 8
D41: Resale Fee | E41: 0.01
C43: Turnover Scaling
D44: 1 | E44: 0
D45: =D44+1 -> 2 | E45: 0
D46: =D45+1 -> 3 | E46: 0
D47: =D46+1 -> 4 | E47: 0
D48: =D47+1 -> 5 | E48: 0.2 | G48: Updated as per recent investigation
D49: =D48+1 -> 6 | E49: 0.4
D50: =D49+1 -> 7 | E50: 0.6 | G50: complete
D51: =D50+1 -> 8 | E51: 0.8 | G51: complete
D52: =D51+1 -> 9 | E52: 1
D53: =D52+1 -> 10 | E53: 1
D54: =D53+1 -> 11 | E54: 1
D55: =D54+1 -> 12 | E55: 1
D56: =D55+1 -> 13 | E56: 1
D57: =D56+1 -> 14 | E57: 1
D58: =D57+1 -> 15 | E58: 1
C60: Terminal Value
D61: Discount Rate | E61: 0.175 | G61: Valuer used ~14%
G62: JLL evidence
B64: GROWTH & INFLATION
D66: Capital Growth | E66: 0.02 | G66: happy
D67: Inflation - Costs | E67: 0.02 | G67: break in 2 | H67: Construction | I67: 0.02
D68: Inflation - Lease | E68: 0.02 | H68: Opex | I68: 0.035
B71: DATA VALIDATION REFERENCES
D73: Land | E73: Ownership | F73: Operating Lease
D74: Typology | E74: House | F74: Apartment
D75: Village Star Rating | E75: 3 | F75: 3.5 | G75: 4 | H75: 4.5

Sheet Cashflow
D1: Period | J1: 1 | K1: 2 | L1: 3 | M1: 4 | N1: 5 | O1: 6 | P1: 7 | Q1: 8 | R1: 9 | S1: 10 | T1: 11 | U1: 12 | V1: 13 | W1: 14 | X1: 15 | Y1: 16 | Z1: 17 | AA1: 18 | AB1: 19 | AC1: 20 | AD1: 21 | AE1: 22 | AF1: 23 | AG1: 24 | AH1: 25 | AI1: 26 | AJ1: 27 | AK1: 28 | AL1: 29 | AM1: 30 | AN1: 31 | AO1: 32 | AP1: 33 | AQ1: 34 | AR1: 35 | AS1: 36 | AT1: 37 | AU1: 38 | AV1: 39 | AW1: 40 | AX1: 41 | AY1: 42 | AZ1: 43 | BA1: 44 | BB1: 45 | BC1: 46 | BD1: 47 | BE1: 48 | BF1: 49 | BG1: 50 | BH1: 51 | BI1: 52 | BJ1: 53 | BK1: 54 | BL1: 55 | BM1: 56 | BN1: 57 | BO1: 58 | BP1: 59 | BQ1: 60 | BR1: 61 | BS1: 62 | BT1: 63 | BU1: 64 | BV1: 65 | BW1: 66 | BX1: 67 | BY1: 68 | BZ1: 69 | CA1: 70 | CB1: 71 | CC1: 72 | CD1: 73 | CE1: 74 | CF1: 75 | CG1: 76 | CH1: 77 | CI1: 78 | CJ1: 79 | CK1: 80 | CL1: 81 | CM1: 82 | CN1: 83 | CO1: 84 | CP1: 85 | CQ1: 86 | CR1: 87 | CS1: 88 | CT1: 89 | CU1: 90 | CV1: 91 | CW1: 92 | CX1: 93 | CY1: 94 | CZ1: 95 | DA1: 96 | DB1: 97 | DC1: 98 | DD1: 99 | DE1: 100 | DF1: 101 | DG1: 102 | DH1: 103 | DI1: 104 | DJ1: 105 | DK1: 106 | DL1: 107 | DM1: 108 | DN1: 109 | DO1: 110 | DP1: 111 | DQ1: 112 | DR1: 113 | DS1: 114 | DT1: 115 | DU1: 116 | DV1: 117 | DW1: 118 | DX1: 119 | DY1: 120 | DZ1: 121 | EA1: 122 | EB1: 123 | EC1: 124 | ED1: 125 | EE1: 126 | EF1: 127 | EG1: 128 | EH1: 129 | EI1: 130 | EJ1: 131 | EK1: 132 | EL1: 133 | EM1: 134 | EN1: 135 | EO1: 136 | EP1: 137 | EQ1: 138 | ER1: 139 | ES1: 140 | ET1: 141 | EU1: 142 | EV1: 143 | EW1: 144 | EX1: 145 | EY1: 146 | EZ1: 147 | FA1: 148 | FB1: 149 | FC1: 150 | FD1: 151 | FE1: 152 | FF1: 153 | FG1: 154 | FH1: 155 | FI1: 156 | FJ1: 157 | FK1: 158 | FL1: 159 | FM1: 160 | FN1: 161 | FO1: 162 | FP1: 163 | FQ1: 164 | FR1: 165 | FS1: 166 | FT1: 167 | FU1: 168 | FV1: 169 | FW1: 170 | FX1: 171 | FY1: 172 | FZ1: 173 | GA1: 174 | GB1: 175 | GC1: 176 | GD1: 177 | GE1: 178 | GF1: 179 | GG1: 180
D2: Date | J2: ='Model Inputs'!E4 -> 46203 | K2: =EOMONTH(J2,12/Periodicity) -> 46234 | L2: =EOMONTH(K2,12/Periodicity) -> 46265 | M2: =EOMONTH(L2,12/Periodicity) -> 46295 | N2: =EOMONTH(M2,12/Periodicity) -> 46326 | O2: =EOMONTH(N2,12/Periodicity) -> 46356 | P2: =EOMONTH(O2,12/Periodicity) -> 46387 | Q2: =EOMONTH(P2,12/Periodicity) -> 46418 | R2: =EOMONTH(Q2,12/Periodicity) -> 46446 | ... GG2: =EOMONTH(GF2,12/Periodicity) -> 51652
D3: Development Phase | J3: =(SUM(J77:$GG$77)>0)*1 -> 1 | K3: =(SUM(K77:$GG$77)>0)*1 -> 1 | L3: =(SUM(L77:$GG$77)>0)*1 -> 1 | M3: =(SUM(M77:$GG$77)>0)*1 -> 1 | N3: =(SUM(N77:$GG$77)>0)*1 -> 1 | O3: =(SUM(O77:$GG$77)>0)*1 -> 1 | P3: =(SUM(P77:$GG$77)>0)*1 -> 1 | Q3: =(SUM(Q77:$GG$77)>0)*1 -> 1 | ... GG3: =(SUM(GG77:$GG$77)>0)*1 -> 0
D4: Operating Phase | J4: =(J3=0)*1 -> 0 | K4: =(K3=0)*1 -> 0 | L4: =(L3=0)*1 -> 0 | M4: =(M3=0)*1 -> 0 | N4: =(N3=0)*1 -> 0 | O4: =(O3=0)*1 -> 0 | P4: =(P3=0)*1 -> 0 | Q4: =(Q3=0)*1 -> 0 | ... GG4: =(GG3=0)*1 -> 1
D5: Project Year | J5: =ROUNDUP(SUM($J3:J4)/Periodicity,0) -> 1 | K5: =ROUNDUP(SUM($J3:K4)/Periodicity,0) -> 1 | L5: =ROUNDUP(SUM($J3:L4)/Periodicity,0) -> 1 | M5: =ROUNDUP(SUM($J3:M4)/Periodicity,0) -> 1 | N5: =ROUNDUP(SUM($J3:N4)/Periodicity,0) -> 1 | O5: =ROUNDUP(SUM($J3:O4)/Periodicity,0) -> 1 | P5: =ROUNDUP(SUM($J3:P4)/Periodicity,0) -> 1 | Q5: =ROUNDUP(SUM($J3:Q4)/Periodicity,0) -> 1 | ... GG5: =ROUNDUP(SUM($J3:GG4)/Periodicity,0) -> 15
D6: Operating Year | J6: =ROUNDUP(SUM($J4:J4)/Periodicity,0) -> 0 | K6: =ROUNDUP(SUM($J4:K4)/Periodicity,0) -> 0 | L6: =ROUNDUP(SUM($J4:L4)/Periodicity,0) -> 0 | M6: =ROUNDUP(SUM($J4:M4)/Periodicity,0) -> 0 | N6: =ROUNDUP(SUM($J4:N4)/Periodicity,0) -> 0 | O6: =ROUNDUP(SUM($J4:O4)/Periodicity,0) -> 0 | P6: =ROUNDUP(SUM($J4:P4)/Periodicity,0) -> 0 | Q6: =ROUNDUP(SUM($J4:Q4)/Periodicity,0) -> 0 | ... GG6: =ROUNDUP(SUM($J4:GG4)/Periodicity,0) -> 10
D8: Inflation Factor - Capital Growth | J8: =(1+'Model Inputs'!$E$66)^(J$5-1) -> 1 | K8: =(1+'Model Inputs'!$E$66)^(K$5-1) -> 1 | L8: =(1+'Model Inputs'!$E$66)^(L$5-1) -> 1 | M8: =(1+'Model Inputs'!$E$66)^(M$5-1) -> 1 | N8: =(1+'Model Inputs'!$E$66)^(N$5-1) -> 1 | O8: =(1+'Model Inputs'!$E$66)^(O$5-1) -> 1 | P8: =(1+'Model Inputs'!$E$66)^(P$5-1) -> 1 | Q8: =(1+'Model Inputs'!$E$66)^(Q$5-1) -> 1 | ... GG8: =(1+'Model Inputs'!$E$66)^(GG$5-1) -> 1.3194788
D9: Inflation Factor - Costs | J9: =(1+'Model Inputs'!$E$67)^(J$5-1) -> 1 | K9: =(1+'Model Inputs'!$E$67)^(K$5-1) -> 1 | L9: =(1+'Model Inputs'!$E$67)^(L$5-1) -> 1 | M9: =(1+'Model Inputs'!$E$67)^(M$5-1) -> 1 | N9: =(1+'Model Inputs'!$E$67)^(N$5-1) -> 1 | O9: =(1+'Model Inputs'!$E$67)^(O$5-1) -> 1 | P9: =(1+'Model Inputs'!$E$67)^(P$5-1) -> 1 | Q9: =(1+'Model Inputs'!$E$67)^(Q$5-1) -> 1 | ... GG9: =(1+'Model Inputs'!$E$67)^(GG$5-1) -> 1.3194788
D10: Inflation Factor - Lease | J10: =(1+'Model Inputs'!$E$68)^(J$5-1) -> 1 | K10: =(1+'Model Inputs'!$E$68)^(K$5-1) -> 1 | L10: =(1+'Model Inputs'!$E$68)^(L$5-1) -> 1 | M10: =(1+'Model Inputs'!$E$68)^(M$5-1) -> 1 | N10: =(1+'Model Inputs'!$E$68)^(N$5-1) -> 1 | O10: =(1+'Model Inputs'!$E$68)^(O$5-1) -> 1 | P10: =(1+'Model Inputs'!$E$68)^(P$5-1) -> 1 | Q10: =(1+'Model Inputs'!$E$68)^(Q$5-1) -> 1 | ... GG10: =(1+'Model Inputs'!$E$68)^(GG$5-1) -> 1.3194788
B13: TIMING
C15: Land Development - Stages & Allocation | E15: Allocation | G15: Commencement | H15: Duration
D16: ='Project Inputs'!D175 -> Stage 1 | E16: ='Project Inputs'!G175 -> 0.4 | G16: ='Project Inputs'!E175 -> 6 | H16: ='Project Inputs'!F175 -> 8 | J16: =IF($E16=0,0,AND(J$1>=$G16,J$1<SUM($G16:$H16))*($E16/$H16)) -> 0 | K16: =IF($E16=0,0,AND(K$1>=$G16,K$1<SUM($G16:$H16))*($E16/$H16)) -> 0 | L16: =IF($E16=0,0,AND(L$1>=$G16,L$1<SUM($G16:$H16))*($E16/$H16)) -> 0 | M16: =IF($E16=0,0,AND(M$1>=$G16,M$1<SUM($G16:$H16))*($E16/$H16)) -> 0 | N16: =IF($E16=0,0,AND(N$1>=$G16,N$1<SUM($G16:$H16))*($E16/$H16)) -> 0 | O16: =IF($E16=0,0,AND(O$1>=$G16,O$1<SUM($G16:$H16))*($E16/$H16)) -> 0.05 | P16: =IF($E16=0,0,AND(P$1>=$G16,P$1<SUM($G16:$H16))*($E16/$H16)) -> 0.05 | Q16: =IF($E16=0,0,AND(Q$1>=$G16,Q$1<SUM($G16:$H16))*($E16/$H16)) -> 0.05 | ... GG16: =IF($E16=0,0,AND(GG$1>=$G16,GG$1<SUM($G16:$H16))*($E16/$H16)) -> 0
D17: ='Project Inputs'!D176 -> Stage 2 | E17: ='Project Inputs'!G176 -> 0.3 | G17: ='Project Inputs'!E176 -> 18 | H17: ='Project Inputs'!F176 -> 6 | J17: =IF($E17=0,0,AND(J$1>=$G17,J$1<SUM($G17:$H17))*($E17/$H17)) -> 0 | K17: =IF($E17=0,0,AND(K$1>=$G17,K$1<SUM($G17:$H17))*($E17/$H17)) -> 0 | L17: =IF($E17=0,0,AND(L$1>=$G17,L$1<SUM($G17:$H17))*($E17/$H17)) -> 0 | M17: =IF($E17=0,0,AND(M$1>=$G17,M$1<SUM($G17:$H17))*($E17/$H17)) -> 0 | N17: =IF($E17=0,0,AND(N$1>=$G17,N$1<SUM($G17:$H17))*($E17/$H17)) -> 0 | O17: =IF($E17=0,0,AND(O$1>=$G17,O$1<SUM($G17:$H17))*($E17/$H17)) -> 0 | P17: =IF($E17=0,0,AND(P$1>=$G17,P$1<SUM($G17:$H17))*($E17/$H17)) -> 0 | Q17: =IF($E17=0,0,AND(Q$1>=$G17,Q$1<SUM($G17:$H17))*($E17/$H17)) -> 0 | ... GG17: =IF($E17=0,0,AND(GG$1>=$G17,GG$1<SUM($G17:$H17))*($E17/$H17)) -> 0
D18: ='Project Inputs'!D177 -> Stage 3 | E18: ='Project Inputs'!G177 -> 0.3 | G18: ='Project Inputs'!E177 -> 30 | H18: ='Project Inputs'!F177 -> 6 | J18: =IF($E18=0,0,AND(J$1>=$G18,J$1<SUM($G18:$H18))*($E18/$H18)) -> 0 | K18: =IF($E18=0,0,AND(K$1>=$G18,K$1<SUM($G18:$H18))*($E18/$H18)) -> 0 | L18: =IF($E18=0,0,AND(L$1>=$G18,L$1<SUM($G18:$H18))*($E18/$H18)) -> 0 | M18: =IF($E18=0,0,AND(M$1>=$G18,M$1<SUM($G18:$H18))*($E18/$H18)) -> 0 | N18: =IF($E18=0,0,AND(N$1>=$G18,N$1<SUM($G18:$H18))*($E18/$H18)) -> 0 | O18: =IF($E18=0,0,AND(O$1>=$G18,O$1<SUM($G18:$H18))*($E18/$H18)) -> 0 | P18: =IF($E18=0,0,AND(P$1>=$G18,P$1<SUM($G18:$H18))*($E18/$H18)) -> 0 | Q18: =IF($E18=0,0,AND(Q$1>=$G18,Q$1<SUM($G18:$H18))*($E18/$H18)) -> 0 | ... GG18: =IF($E18=0,0,AND(GG$1>=$G18,GG$1<SUM($G18:$H18))*($E18/$H18)) -> 0
D19: ='Project Inputs'!D178 -> Stage 4 | E19: ='Project Inputs'!G178 -> 0 | G19: ='Project Inputs'!E178 -> 0 | H19: ='Project Inputs'!F178 -> 0 | J19: =IF($E19=0,0,AND(J$1>=$G19,J$1<SUM($G19:$H19))*($E19/$H19)) -> 0 | K19: =IF($E19=0,0,AND(K$1>=$G19,K$1<SUM($G19:$H19))*($E19/$H19)) -> 0 | L19: =IF($E19=0,0,AND(L$1>=$G19,L$1<SUM($G19:$H19))*($E19/$H19)) -> 0 | M19: =IF($E19=0,0,AND(M$1>=$G19,M$1<SUM($G19:$H19))*($E19/$H19)) -> 0 | N19: =IF($E19=0,0,AND(N$1>=$G19,N$1<SUM($G19:$H19))*($E19/$H19)) -> 0 | O19: =IF($E19=0,0,AND(O$1>=$G19,O$1<SUM($G19:$H19))*($E19/$H19)) -> 0 | P19: =IF($E19=0,0,AND(P$1>=$G19,P$1<SUM($G19:$H19))*($E19/$H19)) -> 0 | Q19: =IF($E19=0,0,AND(Q$1>=$G19,Q$1<SUM($G19:$H19))*($E19/$H19)) -> 0 | ... GG19: =IF($E19=0,0,AND(GG$1>=$G19,GG$1<SUM($G19:$H19))*($E19/$H19)) -> 0
D20: ='Project Inputs'!D179 -> Stage 5 | E20: ='Project Inputs'!G179 -> 0 | G20: ='Project Inputs'!E179 -> 0 | H20: ='Project Inputs'!F179 -> 0 | J20: =IF($E20=0,0,AND(J$1>=$G20,J$1<SUM($G20:$H20))*($E20/$H20)) -> 0 | K20: =IF($E20=0,0,AND(K$1>=$G20,K$1<SUM($G20:$H20))*($E20/$H20)) -> 0 | L20: =IF($E20=0,0,AND(L$1>=$G20,L$1<SUM($G20:$H20))*($E20/$H20)) -> 0 | M20: =IF($E20=0,0,AND(M$1>=$G20,M$1<SUM($G20:$H20))*($E20/$H20)) -> 0 | N20: =IF($E20=0,0,AND(N$1>=$G20,N$1<SUM($G20:$H20))*($E20/$H20)) -> 0 | O20: =IF($E20=0,0,AND(O$1>=$G20,O$1<SUM($G20:$H20))*($E20/$H20)) -> 0 | P20: =IF($E20=0,0,AND(P$1>=$G20,P$1<SUM($G20:$H20))*($E20/$H20)) -> 0 | Q20: =IF($E20=0,0,AND(Q$1>=$G20,Q$1<SUM($G20:$H20))*($E20/$H20)) -> 0 | ... GG20: =IF($E20=0,0,AND(GG$1>=$G20,GG$1<SUM($G20:$H20))*($E20/$H20)) -> 0
J21: =SUM(J16:J20) -> 0 | K21: =SUM(K16:K20) -> 0 | L21: =SUM(L16:L20) -> 0 | M21: =SUM(M16:M20) -> 0 | N21: =SUM(N16:N20) -> 0 | O21: =SUM(O16:O20) -> 0.05 | P21: =SUM(P16:P20) -> 0.05 | Q21: =SUM(Q16:Q20) -> 0.05 | ... GG21: =SUM(GG16:GG20) -> 0
C23: Vertical Construction - Timing | G23: Commencement | H23: Duration
D24: {=_xlfn.SEQUENCE('Project Inputs'!$E$190)} -> 1 | G24: ='Project Inputs'!E183*(D24>0) -> 16 | H24: ='Project Inputs'!$E$184*(D24>0) -> 3 | J24: =AND(J$1>=$G24,J$1<SUM($G24:$H24))*1 -> 0 | K24: =AND(K$1>=$G24,K$1<SUM($G24:$H24))*1 -> 0 | L24: =AND(L$1>=$G24,L$1<SUM($G24:$H24))*1 -> 0 | M24: =AND(M$1>=$G24,M$1<SUM($G24:$H24))*1 -> 0 | N24: =AND(N$1>=$G24,N$1<SUM($G24:$H24))*1 -> 0 | O24: =AND(O$1>=$G24,O$1<SUM($G24:$H24))*1 -> 0 | P24: =AND(P$1>=$G24,P$1<SUM($G24:$H24))*1 -> 0 | Q24: =AND(Q$1>=$G24,Q$1<SUM($G24:$H24))*1 -> 0 | ... GG24: =AND(GG$1>=$G24,GG$1<SUM($G24:$H24))*1 -> 0
D25: 2 | G25: =(G24+'Project Inputs'!$E$185)*(D25>0) -> 19 | H25: ='Project Inputs'!$E$184*(D25>0) -> 3 | J25: =AND(J$1>=$G25,J$1<SUM($G25:$H25))*1 -> 0 | K25: =AND(K$1>=$G25,K$1<SUM($G25:$H25))*1 -> 0 | L25: =AND(L$1>=$G25,L$1<SUM($G25:$H25))*1 -> 0 | M25: =AND(M$1>=$G25,M$1<SUM($G25:$H25))*1 -> 0 | N25: =AND(N$1>=$G25,N$1<SUM($G25:$H25))*1 -> 0 | O25: =AND(O$1>=$G25,O$1<SUM($G25:$H25))*1 -> 0 | P25: =AND(P$1>=$G25,P$1<SUM($G25:$H25))*1 -> 0 | Q25: =AND(Q$1>=$G25,Q$1<SUM($G25:$H25))*1 -> 0 | ... GG25: =AND(GG$1>=$G25,GG$1<SUM($G25:$H25))*1 -> 0
D26: 3 | G26: =(G25+'Project Inputs'!$E$185)*(D26>0) -> 22 | H26: ='Project Inputs'!$E$184*(D26>0) -> 3 | J26: =AND(J$1>=$G26,J$1<SUM($G26:$H26))*1 -> 0 | K26: =AND(K$1>=$G26,K$1<SUM($G26:$H26))*1 -> 0 | L26: =AND(L$1>=$G26,L$1<SUM($G26:$H26))*1 -> 0 | M26: =AND(M$1>=$G26,M$1<SUM($G26:$H26))*1 -> 0 | N26: =AND(N$1>=$G26,N$1<SUM($G26:$H26))*1 -> 0 | O26: =AND(O$1>=$G26,O$1<SUM($G26:$H26))*1 -> 0 | P26: =AND(P$1>=$G26,P$1<SUM($G26:$H26))*1 -> 0 | Q26: =AND(Q$1>=$G26,Q$1<SUM($G26:$H26))*1 -> 0 | ... GG26: =AND(GG$1>=$G26,GG$1<SUM($G26:$H26))*1 -> 0
D27: 4 | G27: =(G26+'Project Inputs'!$E$185)*(D27>0) -> 25 | H27: ='Project Inputs'!$E$184*(D27>0) -> 3 | J27: =AND(J$1>=$G27,J$1<SUM($G27:$H27))*1 -> 0 | K27: =AND(K$1>=$G27,K$1<SUM($G27:$H27))*1 -> 0 | L27: =AND(L$1>=$G27,L$1<SUM($G27:$H27))*1 -> 0 | M27: =AND(M$1>=$G27,M$1<SUM($G27:$H27))*1 -> 0 | N27: =AND(N$1>=$G27,N$1<SUM($G27:$H27))*1 -> 0 | O27: =AND(O$1>=$G27,O$1<SUM($G27:$H27))*1 -> 0 | P27: =AND(P$1>=$G27,P$1<SUM($G27:$H27))*1 -> 0 | Q27: =AND(Q$1>=$G27,Q$1<SUM($G27:$H27))*1 -> 0 | ... GG27: =AND(GG$1>=$G27,GG$1<SUM($G27:$H27))*1 -> 0
D28: 5 | G28: =(G27+'Project Inputs'!$E$185)*(D28>0) -> 28 | H28: ='Project Inputs'!$E$184*(D28>0) -> 3 | J28: =AND(J$1>=$G28,J$1<SUM($G28:$H28))*1 -> 0 | K28: =AND(K$1>=$G28,K$1<SUM($G28:$H28))*1 -> 0 | L28: =AND(L$1>=$G28,L$1<SUM($G28:$H28))*1 -> 0 | M28: =AND(M$1>=$G28,M$1<SUM($G28:$H28))*1 -> 0 | N28: =AND(N$1>=$G28,N$1<SUM($G28:$H28))*1 -> 0 | O28: =AND(O$1>=$G28,O$1<SUM($G28:$H28))*1 -> 0 | P28: =AND(P$1>=$G28,P$1<SUM($G28:$H28))*1 -> 0 | Q28: =AND(Q$1>=$G28,Q$1<SUM($G28:$H28))*1 -> 0 | ... GG28: =AND(GG$1>=$G28,GG$1<SUM($G28:$H28))*1 -> 0
D29: 6 | G29: =(G28+'Project Inputs'!$E$185)*(D29>0) -> 31 | H29: ='Project Inputs'!$E$184*(D29>0) -> 3 | J29: =AND(J$1>=$G29,J$1<SUM($G29:$H29))*1 -> 0 | K29: =AND(K$1>=$G29,K$1<SUM($G29:$H29))*1 -> 0 | L29: =AND(L$1>=$G29,L$1<SUM($G29:$H29))*1 -> 0 | M29: =AND(M$1>=$G29,M$1<SUM($G29:$H29))*1 -> 0 | N29: =AND(N$1>=$G29,N$1<SUM($G29:$H29))*1 -> 0 | O29: =AND(O$1>=$G29,O$1<SUM($G29:$H29))*1 -> 0 | P29: =AND(P$1>=$G29,P$1<SUM($G29:$H29))*1 -> 0 | Q29: =AND(Q$1>=$G29,Q$1<SUM($G29:$H29))*1 -> 0 | ... GG29: =AND(GG$1>=$G29,GG$1<SUM($G29:$H29))*1 -> 0
D30: 7 | G30: =(G29+'Project Inputs'!$E$185)*(D30>0) -> 34 | H30: ='Project Inputs'!$E$184*(D30>0) -> 3 | J30: =AND(J$1>=$G30,J$1<SUM($G30:$H30))*1 -> 0 | K30: =AND(K$1>=$G30,K$1<SUM($G30:$H30))*1 -> 0 | L30: =AND(L$1>=$G30,L$1<SUM($G30:$H30))*1 -> 0 | M30: =AND(M$1>=$G30,M$1<SUM($G30:$H30))*1 -> 0 | N30: =AND(N$1>=$G30,N$1<SUM($G30:$H30))*1 -> 0 | O30: =AND(O$1>=$G30,O$1<SUM($G30:$H30))*1 -> 0 | P30: =AND(P$1>=$G30,P$1<SUM($G30:$H30))*1 -> 0 | Q30: =AND(Q$1>=$G30,Q$1<SUM($G30:$H30))*1 -> 0 | ... GG30: =AND(GG$1>=$G30,GG$1<SUM($G30:$H30))*1 -> 0
D31: 8 | G31: =(G30+'Project Inputs'!$E$185)*(D31>0) -> 37 | H31: ='Project Inputs'!$E$184*(D31>0) -> 3 | J31: =AND(J$1>=$G31,J$1<SUM($G31:$H31))*1 -> 0 | K31: =AND(K$1>=$G31,K$1<SUM($G31:$H31))*1 -> 0 | L31: =AND(L$1>=$G31,L$1<SUM($G31:$H31))*1 -> 0 | M31: =AND(M$1>=$G31,M$1<SUM($G31:$H31))*1 -> 0 | N31: =AND(N$1>=$G31,N$1<SUM($G31:$H31))*1 -> 0 | O31: =AND(O$1>=$G31,O$1<SUM($G31:$H31))*1 -> 0 | P31: =AND(P$1>=$G31,P$1<SUM($G31:$H31))*1 -> 0 | Q31: =AND(Q$1>=$G31,Q$1<SUM($G31:$H31))*1 -> 0 | ... GG31: =AND(GG$1>=$G31,GG$1<SUM($G31:$H31))*1 -> 0
D32: 9 | G32: =(G31+'Project Inputs'!$E$185)*(D32>0) -> 40 | H32: ='Project Inputs'!$E$184*(D32>0) -> 3 | J32: =AND(J$1>=$G32,J$1<SUM($G32:$H32))*1 -> 0 | K32: =AND(K$1>=$G32,K$1<SUM($G32:$H32))*1 -> 0 | L32: =AND(L$1>=$G32,L$1<SUM($G32:$H32))*1 -> 0 | M32: =AND(M$1>=$G32,M$1<SUM($G32:$H32))*1 -> 0 | N32: =AND(N$1>=$G32,N$1<SUM($G32:$H32))*1 -> 0 | O32: =AND(O$1>=$G32,O$1<SUM($G32:$H32))*1 -> 0 | P32: =AND(P$1>=$G32,P$1<SUM($G32:$H32))*1 -> 0 | Q32: =AND(Q$1>=$G32,Q$1<SUM($G32:$H32))*1 -> 0 | ... GG32: =AND(GG$1>=$G32,GG$1<SUM($G32:$H32))*1 -> 0
D33: 10 | G33: =(G32+'Project Inputs'!$E$185)*(D33>0) -> 43 | H33: ='Project Inputs'!$E$184*(D33>0) -> 3 | J33: =AND(J$1>=$G33,J$1<SUM($G33:$H33))*1 -> 0 | K33: =AND(K$1>=$G33,K$1<SUM($G33:$H33))*1 -> 0 | L33: =AND(L$1>=$G33,L$1<SUM($G33:$H33))*1 -> 0 | M33: =AND(M$1>=$G33,M$1<SUM($G33:$H33))*1 -> 0 | N33: =AND(N$1>=$G33,N$1<SUM($G33:$H33))*1 -> 0 | O33: =AND(O$1>=$G33,O$1<SUM($G33:$H33))*1 -> 0 | P33: =AND(P$1>=$G33,P$1<SUM($G33:$H33))*1 -> 0 | Q33: =AND(Q$1>=$G33,Q$1<SUM($G33:$H33))*1 -> 0 | ... GG33: =AND(GG$1>=$G33,GG$1<SUM($G33:$H33))*1 -> 0
D34: 11 | G34: =(G33+'Project Inputs'!$E$185)*(D34>0) -> 46 | H34: ='Project Inputs'!$E$184*(D34>0) -> 3 | J34: =AND(J$1>=$G34,J$1<SUM($G34:$H34))*1 -> 0 | K34: =AND(K$1>=$G34,K$1<SUM($G34:$H34))*1 -> 0 | L34: =AND(L$1>=$G34,L$1<SUM($G34:$H34))*1 -> 0 | M34: =AND(M$1>=$G34,M$1<SUM($G34:$H34))*1 -> 0 | N34: =AND(N$1>=$G34,N$1<SUM($G34:$H34))*1 -> 0 | O34: =AND(O$1>=$G34,O$1<SUM($G34:$H34))*1 -> 0 | P34: =AND(P$1>=$G34,P$1<SUM($G34:$H34))*1 -> 0 | Q34: =AND(Q$1>=$G34,Q$1<SUM($G34:$H34))*1 -> 0 | ... GG34: =AND(GG$1>=$G34,GG$1<SUM($G34:$H34))*1 -> 0
D35: 12 | G35: =(G34+'Project Inputs'!$E$185)*(D35>0) -> 49 | H35: ='Project Inputs'!$E$184*(D35>0) -> 3 | J35: =AND(J$1>=$G35,J$1<SUM($G35:$H35))*1 -> 0 | K35: =AND(K$1>=$G35,K$1<SUM($G35:$H35))*1 -> 0 | L35: =AND(L$1>=$G35,L$1<SUM($G35:$H35))*1 -> 0 | M35: =AND(M$1>=$G35,M$1<SUM($G35:$H35))*1 -> 0 | N35: =AND(N$1>=$G35,N$1<SUM($G35:$H35))*1 -> 0 | O35: =AND(O$1>=$G35,O$1<SUM($G35:$H35))*1 -> 0 | P35: =AND(P$1>=$G35,P$1<SUM($G35:$H35))*1 -> 0 | Q35: =AND(Q$1>=$G35,Q$1<SUM($G35:$H35))*1 -> 0 | ... GG35: =AND(GG$1>=$G35,GG$1<SUM($G35:$H35))*1 -> 0
D36: 13 | G36: =(G35+'Project Inputs'!$E$185)*(D36>0) -> 52 | H36: ='Project Inputs'!$E$184*(D36>0) -> 3 | J36: =AND(J$1>=$G36,J$1<SUM($G36:$H36))*1 -> 0 | K36: =AND(K$1>=$G36,K$1<SUM($G36:$H36))*1 -> 0 | L36: =AND(L$1>=$G36,L$1<SUM($G36:$H36))*1 -> 0 | M36: =AND(M$1>=$G36,M$1<SUM($G36:$H36))*1 -> 0 | N36: =AND(N$1>=$G36,N$1<SUM($G36:$H36))*1 -> 0 | O36: =AND(O$1>=$G36,O$1<SUM($G36:$H36))*1 -> 0 | P36: =AND(P$1>=$G36,P$1<SUM($G36:$H36))*1 -> 0 | Q36: =AND(Q$1>=$G36,Q$1<SUM($G36:$H36))*1 -> 0 | ... GG36: =AND(GG$1>=$G36,GG$1<SUM($G36:$H36))*1 -> 0
... D41: 18 | G41: =(G40+'Project Inputs'!$E$185)*(D41>0) -> 67 | H41: ='Project Inputs'!$E$184*(D41>0) -> 3 | J41: =AND(J$1>=$G41,J$1<SUM($G41:$H41))*1 -> 0 | K41: =AND(K$1>=$G41,K$1<SUM($G41:$H41))*1 -> 0 | L41: =AND(L$1>=$G41,L$1<SUM($G41:$H41))*1 -> 0 | M41: =AND(M$1>=$G41,M$1<SUM($G41:$H41))*1 -> 0 | N41: =AND(N$1>=$G41,N$1<SUM($G41:$H41))*1 -> 0 | O41: =AND(O$1>=$G41,O$1<SUM($G41:$H41))*1 -> 0 | P41: =AND(P$1>=$G41,P$1<SUM($G41:$H41))*1 -> 0 | Q41: =AND(Q$1>=$G41,Q$1<SUM($G41:$H41))*1 -> 0 | ... GG41: =AND(GG$1>=$G41,GG$1<SUM($G41:$H41))*1 -> 0
G42: =(G41+'Project Inputs'!$E$185)*(D42>0) -> 0 | H42: ='Project Inputs'!$E$184*(D42>0) -> 0 | J42: =AND(J$1>=$G42,J$1<SUM($G42:$H42))*1 -> 0 | K42: =AND(K$1>=$G42,K$1<SUM($G42:$H42))*1 -> 0 | L42: =AND(L$1>=$G42,L$1<SUM($G42:$H42))*1 -> 0 | M42: =AND(M$1>=$G42,M$1<SUM($G42:$H42))*1 -> 0 | N42: =AND(N$1>=$G42,N$1<SUM($G42:$H42))*1 -> 0 | O42: =AND(O$1>=$G42,O$1<SUM($G42:$H42))*1 -> 0 | P42: =AND(P$1>=$G42,P$1<SUM($G42:$H42))*1 -> 0 | Q42: =AND(Q$1>=$G42,Q$1<SUM($G42:$H42))*1 -> 0 | ... GG42: =AND(GG$1>=$G42,GG$1<SUM($G42:$H42))*1 -> 0
G43: =(G42+'Project Inputs'!$E$185)*(D43>0) -> 0 | H43: ='Project Inputs'!$E$184*(D43>0) -> 0 | J43: =AND(J$1>=$G43,J$1<SUM($G43:$H43))*1 -> 0 | K43: =AND(K$1>=$G43,K$1<SUM($G43:$H43))*1 -> 0 | L43: =AND(L$1>=$G43,L$1<SUM($G43:$H43))*1 -> 0 | M43: =AND(M$1>=$G43,M$1<SUM($G43:$H43))*1 -> 0 | N43: =AND(N$1>=$G43,N$1<SUM($G43:$H43))*1 -> 0 | O43: =AND(O$1>=$G43,O$1<SUM($G43:$H43))*1 -> 0 | P43: =AND(P$1>=$G43,P$1<SUM($G43:$H43))*1 -> 0 | Q43: =AND(Q$1>=$G43,Q$1<SUM($G43:$H43))*1 -> 0 | ... GG43: =AND(GG$1>=$G43,GG$1<SUM($G43:$H43))*1 -> 0
G44: =(G43+'Project Inputs'!$E$185)*(D44>0) -> 0 | H44: ='Project Inputs'!$E$184*(D44>0) -> 0 | J44: =AND(J$1>=$G44,J$1<SUM($G44:$H44))*1 -> 0 | K44: =AND(K$1>=$G44,K$1<SUM($G44:$H44))*1 -> 0 | L44: =AND(L$1>=$G44,L$1<SUM($G44:$H44))*1 -> 0 | M44: =AND(M$1>=$G44,M$1<SUM($G44:$H44))*1 -> 0 | N44: =AND(N$1>=$G44,N$1<SUM($G44:$H44))*1 -> 0 | O44: =AND(O$1>=$G44,O$1<SUM($G44:$H44))*1 -> 0 | P44: =AND(P$1>=$G44,P$1<SUM($G44:$H44))*1 -> 0 | Q44: =AND(Q$1>=$G44,Q$1<SUM($G44:$H44))*1 -> 0 | ... GG44: =AND(GG$1>=$G44,GG$1<SUM($G44:$H44))*1 -> 0
G45: =(G44+'Project Inputs'!$E$185)*(D45>0) -> 0 | H45: ='Project Inputs'!$E$184*(D45>0) -> 0 | J45: =AND(J$1>=$G45,J$1<SUM($G45:$H45))*1 -> 0 | K45: =AND(K$1>=$G45,K$1<SUM($G45:$H45))*1 -> 0 | L45: =AND(L$1>=$G45,L$1<SUM($G45:$H45))*1 -> 0 | M45: =AND(M$1>=$G45,M$1<SUM($G45:$H45))*1 -> 0 | N45: =AND(N$1>=$G45,N$1<SUM($G45:$H45))*1 -> 0 | O45: =AND(O$1>=$G45,O$1<SUM($G45:$H45))*1 -> 0 | P45: =AND(P$1>=$G45,P$1<SUM($G45:$H45))*1 -> 0 | Q45: =AND(Q$1>=$G45,Q$1<SUM($G45:$H45))*1 -> 0 | ... GG45: =AND(GG$1>=$G45,GG$1<SUM($G45:$H45))*1 -> 0
G46: =(G45+'Project Inputs'!$E$185)*(D46>0) -> 0 | H46: ='Project Inputs'!$E$184*(D46>0) -> 0 | J46: =AND(J$1>=$G46,J$1<SUM($G46:$H46))*1 -> 0 | K46: =AND(K$1>=$G46,K$1<SUM($G46:$H46))*1 -> 0 | L46: =AND(L$1>=$G46,L$1<SUM($G46:$H46))*1 -> 0 | M46: =AND(M$1>=$G46,M$1<SUM($G46:$H46))*1 -> 0 | N46: =AND(N$1>=$G46,N$1<SUM($G46:$H46))*1 -> 0 | O46: =AND(O$1>=$G46,O$1<SUM($G46:$H46))*1 -> 0 | P46: =AND(P$1>=$G46,P$1<SUM($G46:$H46))*1 -> 0 | Q46: =AND(Q$1>=$G46,Q$1<SUM($G46:$H46))*1 -> 0 | ... GG46: =AND(GG$1>=$G46,GG$1<SUM($G46:$H46))*1 -> 0
G47: =(G46+'Project Inputs'!$E$185)*(D47>0) -> 0 | H47: ='Project Inputs'!$E$184*(D47>0) -> 0 | J47: =AND(J$1>=$G47,J$1<SUM($G47:$H47))*1 -> 0 | K47: =AND(K$1>=$G47,K$1<SUM($G47:$H47))*1 -> 0 | L47: =AND(L$1>=$G47,L$1<SUM($G47:$H47))*1 -> 0 | M47: =AND(M$1>=$G47,M$1<SUM($G47:$H47))*1 -> 0 | N47: =AND(N$1>=$G47,N$1<SUM($G47:$H47))*1 -> 0 | O47: =AND(O$1>=$G47,O$1<SUM($G47:$H47))*1 -> 0 | P47: =AND(P$1>=$G47,P$1<SUM($G47:$H47))*1 -> 0 | Q47: =AND(Q$1>=$G47,Q$1<SUM($G47:$H47))*1 -> 0 | ... GG47: =AND(GG$1>=$G47,GG$1<SUM($G47:$H47))*1 -> 0
G48: =(G47+'Project Inputs'!$E$185)*(D48>0) -> 0 | H48: ='Project Inputs'!$E$184*(D48>0) -> 0 | J48: =AND(J$1>=$G48,J$1<SUM($G48:$H48))*1 -> 0 | K48: =AND(K$1>=$G48,K$1<SUM($G48:$H48))*1 -> 0 | L48: =AND(L$1>=$G48,L$1<SUM($G48:$H48))*1 -> 0 | M48: =AND(M$1>=$G48,M$1<SUM($G48:$H48))*1 -> 0 | N48: =AND(N$1>=$G48,N$1<SUM($G48:$H48))*1 -> 0 | O48: =AND(O$1>=$G48,O$1<SUM($G48:$H48))*1 -> 0 | P48: =AND(P$1>=$G48,P$1<SUM($G48:$H48))*1 -> 0 | Q48: =AND(Q$1>=$G48,Q$1<SUM($G48:$H48))*1 -> 0 | ... GG48: =AND(GG$1>=$G48,GG$1<SUM($G48:$H48))*1 -> 0
J49: =SUM(J24:J48) -> 0 | K49: =SUM(K24:K48) -> 0 | L49: =SUM(L24:L48) -> 0 | M49: =SUM(M24:M48) -> 0 | N49: =SUM(N24:N48) -> 0 | O49: =SUM(O24:O48) -> 0 | P49: =SUM(P24:P48) -> 0 | Q49: =SUM(Q24:Q48) -> 0 | ... GG49: =SUM(GG24:GG48) -> 0
C51: Vertical Construction - Completion | E51: Units | G51: Completion
D52: {=_xlfn.SEQUENCE('Project Inputs'!$E$190)} -> 1 | E52: ='Project Inputs'!E193*(D52>0) -> 6 | G52: =(G24+H24-1)*(D52>0) -> 18 | J52: =(J$1=$G52)*$E52 -> 0 | K52: =(K$1=$G52)*$E52 -> 0 | L52: =(L$1=$G52)*$E52 -> 0 | M52: =(M$1=$G52)*$E52 -> 0 | N52: =(N$1=$G52)*$E52 -> 0 | O52: =(O$1=$G52)*$E52 -> 0 | P52: =(P$1=$G52)*$E52 -> 0 | Q52: =(Q$1=$G52)*$E52 -> 0 | ... GG52: =(GG$1=$G52)*$E52 -> 0
D53: 2 | E53: ='Project Inputs'!E194*(D53>0) -> 6 | G53: =(G25+H25-1)*(D53>0) -> 21 | J53: =(J$1=$G53)*$E53 -> 0 | K53: =(K$1=$G53)*$E53 -> 0 | L53: =(L$1=$G53)*$E53 -> 0 | M53: =(M$1=$G53)*$E53 -> 0 | N53: =(N$1=$G53)*$E53 -> 0 | O53: =(O$1=$G53)*$E53 -> 0 | P53: =(P$1=$G53)*$E53 -> 0 | Q53: =(Q$1=$G53)*$E53 -> 0 | ... GG53: =(GG$1=$G53)*$E53 -> 0
D54: 3 | E54: ='Project Inputs'!E195*(D54>0) -> 6 | G54: =(G26+H26-1)*(D54>0) -> 24 | J54: =(J$1=$G54)*$E54 -> 0 | K54: =(K$1=$G54)*$E54 -> 0 | L54: =(L$1=$G54)*$E54 -> 0 | M54: =(M$1=$G54)*$E54 -> 0 | N54: =(N$1=$G54)*$E54 -> 0 | O54: =(O$1=$G54)*$E54 -> 0 | P54: =(P$1=$G54)*$E54 -> 0 | Q54: =(Q$1=$G54)*$E54 -> 0 | ... GG54: =(GG$1=$G54)*$E54 -> 0
D55: 4 | E55: ='Project Inputs'!E196*(D55>0) -> 6 | G55: =(G27+H27-1)*(D55>0) -> 27 | J55: =(J$1=$G55)*$E55 -> 0 | K55: =(K$1=$G55)*$E55 -> 0 | L55: =(L$1=$G55)*$E55 -> 0 | M55: =(M$1=$G55)*$E55 -> 0 | N55: =(N$1=$G55)*$E55 -> 0 | O55: =(O$1=$G55)*$E55 -> 0 | P55: =(P$1=$G55)*$E55 -> 0 | Q55: =(Q$1=$G55)*$E55 -> 0 | ... GG55: =(GG$1=$G55)*$E55 -> 0
D56: 5 | E56: ='Project Inputs'!E197*(D56>0) -> 6 | G56: =(G28+H28-1)*(D56>0) -> 30 | J56: =(J$1=$G56)*$E56 -> 0 | K56: =(K$1=$G56)*$E56 -> 0 | L56: =(L$1=$G56)*$E56 -> 0 | M56: =(M$1=$G56)*$E56 -> 0 | N56: =(N$1=$G56)*$E56 -> 0 | O56: =(O$1=$G56)*$E56 -> 0 | P56: =(P$1=$G56)*$E56 -> 0 | Q56: =(Q$1=$G56)*$E56 -> 0 | ... GG56: =(GG$1=$G56)*$E56 -> 0
D57: 6 | E57: ='Project Inputs'!E198*(D57>0) -> 6 | G57: =(G29+H29-1)*(D57>0) -> 33 | J57: =(J$1=$G57)*$E57 -> 0 | K57: =(K$1=$G57)*$E57 -> 0 | L57: =(L$1=$G57)*$E57 -> 0 | M57: =(M$1=$G57)*$E57 -> 0 | N57: =(N$1=$G57)*$E57 -> 0 | O57: =(O$1=$G57)*$E57 -> 0 | P57: =(P$1=$G57)*$E57 -> 0 | Q57: =(Q$1=$G57)*$E57 -> 0 | ... GG57: =(GG$1=$G57)*$E57 -> 0
D58: 7 | E58: ='Project Inputs'!E199*(D58>0) -> 6 | G58: =(G30+H30-1)*(D58>0) -> 36 | J58: =(J$1=$G58)*$E58 -> 0 | K58: =(K$1=$G58)*$E58 -> 0 | L58: =(L$1=$G58)*$E58 -> 0 | M58: =(M$1=$G58)*$E58 -> 0 | N58: =(N$1=$G58)*$E58 -> 0 | O58: =(O$1=$G58)*$E58 -> 0 | P58: =(P$1=$G58)*$E58 -> 0 | Q58: =(Q$1=$G58)*$E58 -> 0 | ... GG58: =(GG$1=$G58)*$E58 -> 0
D59: 8 | E59: ='Project Inputs'!E200*(D59>0) -> 6 | G59: =(G31+H31-1)*(D59>0) -> 39 | J59: =(J$1=$G59)*$E59 -> 0 | K59: =(K$1=$G59)*$E59 -> 0 | L59: =(L$1=$G59)*$E59 -> 0 | M59: =(M$1=$G59)*$E59 -> 0 | N59: =(N$1=$G59)*$E59 -> 0 | O59: =(O$1=$G59)*$E59 -> 0 | P59: =(P$1=$G59)*$E59 -> 0 | Q59: =(Q$1=$G59)*$E59 -> 0 | ... GG59: =(GG$1=$G59)*$E59 -> 0
D60: 9 | E60: ='Project Inputs'!E201*(D60>0) -> 6 | G60: =(G32+H32-1)*(D60>0) -> 42 | J60: =(J$1=$G60)*$E60 -> 0 | K60: =(K$1=$G60)*$E60 -> 0 | L60: =(L$1=$G60)*$E60 -> 0 | M60: =(M$1=$G60)*$E60 -> 0 | N60: =(N$1=$G60)*$E60 -> 0 | O60: =(O$1=$G60)*$E60 -> 0 | P60: =(P$1=$G60)*$E60 -> 0 | Q60: =(Q$1=$G60)*$E60 -> 0 | ... GG60: =(GG$1=$G60)*$E60 -> 0
D61: 10 | E61: ='Project Inputs'!E202*(D61>0) -> 6 | G61: =(G33+H33-1)*(D61>0) -> 45 | J61: =(J$1=$G61)*$E61 -> 0 | K61: =(K$1=$G61)*$E61 -> 0 | L61: =(L$1=$G61)*$E61 -> 0 | M61: =(M$1=$G61)*$E61 -> 0 | N61: =(N$1=$G61)*$E61 -> 0 | O61: =(O$1=$G61)*$E61 -> 0 | P61: =(P$1=$G61)*$E61 -> 0 | Q61: =(Q$1=$G61)*$E61 -> 0 | ... GG61: =(GG$1=$G61)*$E61 -> 0
D62: 11 | E62: ='Project Inputs'!E203*(D62>0) -> 6 | G62: =(G34+H34-1)*(D62>0) -> 48 | J62: =(J$1=$G62)*$E62 -> 0 | K62: =(K$1=$G62)*$E62 -> 0 | L62: =(L$1=$G62)*$E62 -> 0 | M62: =(M$1=$G62)*$E62 -> 0 | N62: =(N$1=$G62)*$E62 -> 0 | O62: =(O$1=$G62)*$E62 -> 0 | P62: =(P$1=$G62)*$E62 -> 0 | Q62: =(Q$1=$G62)*$E62 -> 0 | ... GG62: =(GG$1=$G62)*$E62 -> 0
D63: 12 | E63: ='Project Inputs'!E204*(D63>0) -> 6 | G63: =(G35+H35-1)*(D63>0) -> 51 | J63: =(J$1=$G63)*$E63 -> 0 | K63: =(K$1=$G63)*$E63 -> 0 | L63: =(L$1=$G63)*$E63 -> 0 | M63: =(M$1=$G63)*$E63 -> 0 | N63: =(N$1=$G63)*$E63 -> 0 | O63: =(O$1=$G63)*$E63 -> 0 | P63: =(P$1=$G63)*$E63 -> 0 | Q63: =(Q$1=$G63)*$E63 -> 0 | ... GG63: =(GG$1=$G63)*$E63 -> 0
D64: 13 | E64: ='Project Inputs'!E205*(D64>0) -> 6 | G64: =(G36+H36-1)*(D64>0) -> 54 | J64: =(J$1=$G64)*$E64 -> 0 | K64: =(K$1=$G64)*$E64 -> 0 | L64: =(L$1=$G64)*$E64 -> 0 | M64: =(M$1=$G64)*$E64 -> 0 | N64: =(N$1=$G64)*$E64 -> 0 | O64: =(O$1=$G64)*$E64 -> 0 | P64: =(P$1=$G64)*$E64 -> 0 | Q64: =(Q$1=$G64)*$E64 -> 0 | ... GG64: =(GG$1=$G64)*$E64 -> 0
... D69: 18 | E69: ='Project Inputs'!E210*(D69>0) -> 3 | G69: =(G41+H41-1)*(D69>0) -> 69 | J69: =(J$1=$G69)*$E69 -> 0 | K69: =(K$1=$G69)*$E69 -> 0 | L69: =(L$1=$G69)*$E69 -> 0 | M69: =(M$1=$G69)*$E69 -> 0 | N69: =(N$1=$G69)*$E69 -> 0 | O69: =(O$1=$G69)*$E69 -> 0 | P69: =(P$1=$G69)*$E69 -> 0 | Q69: =(Q$1=$G69)*$E69 -> 0 | ... GG69: =(GG$1=$G69)*$E69 -> 0
E70: ='Project Inputs'!E211*(D70>0) -> 0 | G70: =(G42+H42-1)*(D70>0) -> 0 | J70: =(J$1=$G70)*$E70 -> 0 | K70: =(K$1=$G70)*$E70 -> 0 | L70: =(L$1=$G70)*$E70 -> 0 | M70: =(M$1=$G70)*$E70 -> 0 | N70: =(N$1=$G70)*$E70 -> 0 | O70: =(O$1=$G70)*$E70 -> 0 | P70: =(P$1=$G70)*$E70 -> 0 | Q70: =(Q$1=$G70)*$E70 -> 0 | ... GG70: =(GG$1=$G70)*$E70 -> 0
E71: ='Project Inputs'!E212*(D71>0) -> 0 | G71: =(G43+H43-1)*(D71>0) -> 0 | J71: =(J$1=$G71)*$E71 -> 0 | K71: =(K$1=$G71)*$E71 -> 0 | L71: =(L$1=$G71)*$E71 -> 0 | M71: =(M$1=$G71)*$E71 -> 0 | N71: =(N$1=$G71)*$E71 -> 0 | O71: =(O$1=$G71)*$E71 -> 0 | P71: =(P$1=$G71)*$E71 -> 0 | Q71: =(Q$1=$G71)*$E71 -> 0 | ... GG71: =(GG$1=$G71)*$E71 -> 0
E72: ='Project Inputs'!E213*(D72>0) -> 0 | G72: =(G44+H44-1)*(D72>0) -> 0 | J72: =(J$1=$G72)*$E72 -> 0 | K72: =(K$1=$G72)*$E72 -> 0 | L72: =(L$1=$G72)*$E72 -> 0 | M72: =(M$1=$G72)*$E72 -> 0 | N72: =(N$1=$G72)*$E72 -> 0 | O72: =(O$1=$G72)*$E72 -> 0 | P72: =(P$1=$G72)*$E72 -> 0 | Q72: =(Q$1=$G72)*$E72 -> 0 | ... GG72: =(GG$1=$G72)*$E72 -> 0
E73: ='Project Inputs'!E214*(D73>0) -> 0 | G73: =(G45+H45-1)*(D73>0) -> 0 | J73: =(J$1=$G73)*$E73 -> 0 | K73: =(K$1=$G73)*$E73 -> 0 | L73: =(L$1=$G73)*$E73 -> 0 | M73: =(M$1=$G73)*$E73 -> 0 | N73: =(N$1=$G73)*$E73 -> 0 | O73: =(O$1=$G73)*$E73 -> 0 | P73: =(P$1=$G73)*$E73 -> 0 | Q73: =(Q$1=$G73)*$E73 -> 0 | ... GG73: =(GG$1=$G73)*$E73 -> 0
E74: ='Project Inputs'!E215*(D74>0) -> 0 | G74: =(G46+H46-1)*(D74>0) -> 0 | J74: =(J$1=$G74)*$E74 -> 0 | K74: =(K$1=$G74)*$E74 -> 0 | L74: =(L$1=$G74)*$E74 -> 0 | M74: =(M$1=$G74)*$E74 -> 0 | N74: =(N$1=$G74)*$E74 -> 0 | O74: =(O$1=$G74)*$E74 -> 0 | P74: =(P$1=$G74)*$E74 -> 0 | Q74: =(Q$1=$G74)*$E74 -> 0 | ... GG74: =(GG$1=$G74)*$E74 -> 0
E75: ='Project Inputs'!E216*(D75>0) -> 0 | G75: =(G47+H47-1)*(D75>0) -> 0 | J75: =(J$1=$G75)*$E75 -> 0 | K75: =(K$1=$G75)*$E75 -> 0 | L75: =(L$1=$G75)*$E75 -> 0 | M75: =(M$1=$G75)*$E75 -> 0 | N75: =(N$1=$G75)*$E75 -> 0 | O75: =(O$1=$G75)*$E75 -> 0 | P75: =(P$1=$G75)*$E75 -> 0 | Q75: =(Q$1=$G75)*$E75 -> 0 | ... GG75: =(GG$1=$G75)*$E75 -> 0
E76: ='Project Inputs'!E217*(D76>0) -> 0 | G76: =(G48+H48-1)*(D76>0) -> 0 | J76: =(J$1=$G76)*$E76 -> 0 | K76: =(K$1=$G76)*$E76 -> 0 | L76: =(L$1=$G76)*$E76 -> 0 | M76: =(M$1=$G76)*$E76 -> 0 | N76: =(N$1=$G76)*$E76 -> 0 | O76: =(O$1=$G76)*$E76 -> 0 | P76: =(P$1=$G76)*$E76 -> 0 | Q76: =(Q$1=$G76)*$E76 -> 0 | ... GG76: =(GG$1=$G76)*$E76 -> 0
J77: =SUM(J52:J76) -> 0 | K77: =SUM(K52:K76) -> 0 | L77: =SUM(L52:L76) -> 0 | M77: =SUM(M52:M76) -> 0 | N77: =SUM(N52:N76) -> 0 | O77: =SUM(O52:O76) -> 0 | P77: =SUM(P52:P76) -> 0 | Q77: =SUM(Q52:Q76) -> 0 | ... GG77: =SUM(GG52:GG76) -> 0
C79: Sales | E79: Units | G79: Sale
D80: {=_xlfn.SEQUENCE('Project Inputs'!$E$190)} -> 1 | E80: ='Project Inputs'!E193*(D80>0) -> 6 | G80: =(G52+'Project Inputs'!$E$186)*(D80>0) -> 21 | J80: =(J$1=$G80)*$E80 -> 0 | K80: =(K$1=$G80)*$E80 -> 0 | L80: =(L$1=$G80)*$E80 -> 0 | M80: =(M$1=$G80)*$E80 -> 0 | N80: =(N$1=$G80)*$E80 -> 0 | O80: =(O$1=$G80)*$E80 -> 0 | P80: =(P$1=$G80)*$E80 -> 0 | Q80: =(Q$1=$G80)*$E80 -> 0 | ... GG80: =(GG$1=$G80)*$E80 -> 0
D81: 2 | E81: ='Project Inputs'!E194*(D81>0) -> 6 | G81: =(G53+'Project Inputs'!$E$186)*(D81>0) -> 24 | J81: =(J$1=$G81)*$E81 -> 0 | K81: =(K$1=$G81)*$E81 -> 0 | L81: =(L$1=$G81)*$E81 -> 0 | M81: =(M$1=$G81)*$E81 -> 0 | N81: =(N$1=$G81)*$E81 -> 0 | O81: =(O$1=$G81)*$E81 -> 0 | P81: =(P$1=$G81)*$E81 -> 0 | Q81: =(Q$1=$G81)*$E81 -> 0 | ... GG81: =(GG$1=$G81)*$E81 -> 0
D82: 3 | E82: ='Project Inputs'!E195*(D82>0) -> 6 | G82: =(G54+'Project Inputs'!$E$186)*(D82>0) -> 27 | J82: =(J$1=$G82)*$E82 -> 0 | K82: =(K$1=$G82)*$E82 -> 0 | L82: =(L$1=$G82)*$E82 -> 0 | M82: =(M$1=$G82)*$E82 -> 0 | N82: =(N$1=$G82)*$E82 -> 0 | O82: =(O$1=$G82)*$E82 -> 0 | P82: =(P$1=$G82)*$E82 -> 0 | Q82: =(Q$1=$G82)*$E82 -> 0 | ... GG82: =(GG$1=$G82)*$E82 -> 0
D83: 4 | E83: ='Project Inputs'!E196*(D83>0) -> 6 | G83: =(G55+'Project Inputs'!$E$186)*(D83>0) -> 30 | J83: =(J$1=$G83)*$E83 -> 0 | K83: =(K$1=$G83)*$E83 -> 0 | L83: =(L$1=$G83)*$E83 -> 0 | M83: =(M$1=$G83)*$E83 -> 0 | N83: =(N$1=$G83)*$E83 -> 0 | O83: =(O$1=$G83)*$E83 -> 0 | P83: =(P$1=$G83)*$E83 -> 0 | Q83: =(Q$1=$G83)*$E83 -> 0 | ... GG83: =(GG$1=$G83)*$E83 -> 0
D84: 5 | E84: ='Project Inputs'!E197*(D84>0) -> 6 | G84: =(G56+'Project Inputs'!$E$186)*(D84>0) -> 33 | J84: =(J$1=$G84)*$E84 -> 0 | K84: =(K$1=$G84)*$E84 -> 0 | L84: =(L$1=$G84)*$E84 -> 0 | M84: =(M$1=$G84)*$E84 -> 0 | N84: =(N$1=$G84)*$E84 -> 0 | O84: =(O$1=$G84)*$E84 -> 0 | P84: =(P$1=$G84)*$E84 -> 0 | Q84: =(Q$1=$G84)*$E84 -> 0 | ... GG84: =(GG$1=$G84)*$E84 -> 0
D85: 6 | E85: ='Project Inputs'!E198*(D85>0) -> 6 | G85: =(G57+'Project Inputs'!$E$186)*(D85>0) -> 36 | J85: =(J$1=$G85)*$E85 -> 0 | K85: =(K$1=$G85)*$E85 -> 0 | L85: =(L$1=$G85)*$E85 -> 0 | M85: =(M$1=$G85)*$E85 -> 0 | N85: =(N$1=$G85)*$E85 -> 0 | O85: =(O$1=$G85)*$E85 -> 0 | P85: =(P$1=$G85)*$E85 -> 0 | Q85: =(Q$1=$G85)*$E85 -> 0 | ... GG85: =(GG$1=$G85)*$E85 -> 0
D86: 7 | E86: ='Project Inputs'!E199*(D86>0) -> 6 | G86: =(G58+'Project Inputs'!$E$186)*(D86>0) -> 39 | J86: =(J$1=$G86)*$E86 -> 0 | K86: =(K$1=$G86)*$E86 -> 0 | L86: =(L$1=$G86)*$E86 -> 0 | M86: =(M$1=$G86)*$E86 -> 0 | N86: =(N$1=$G86)*$E86 -> 0 | O86: =(O$1=$G86)*$E86 -> 0 | P86: =(P$1=$G86)*$E86 -> 0 | Q86: =(Q$1=$G86)*$E86 -> 0 | ... GG86: =(GG$1=$G86)*$E86 -> 0
D87: 8 | E87: ='Project Inputs'!E200*(D87>0) -> 6 | G87: =(G59+'Project Inputs'!$E$186)*(D87>0) -> 42 | J87: =(J$1=$G87)*$E87 -> 0 | K87: =(K$1=$G87)*$E87 -> 0 | L87: =(L$1=$G87)*$E87 -> 0 | M87: =(M$1=$G87)*$E87 -> 0 | N87: =(N$1=$G87)*$E87 -> 0 | O87: =(O$1=$G87)*$E87 -> 0 | P87: =(P$1=$G87)*$E87 -> 0 | Q87: =(Q$1=$G87)*$E87 -> 0 | ... GG87: =(GG$1=$G87)*$E87 -> 0
D88: 9 | E88: ='Project Inputs'!E201*(D88>0) -> 6 | G88: =(G60+'Project Inputs'!$E$186)*(D88>0) -> 45 | J88: =(J$1=$G88)*$E88 -> 0 | K88: =(K$1=$G88)*$E88 -> 0 | L88: =(L$1=$G88)*$E88 -> 0 | M88: =(M$1=$G88)*$E88 -> 0 | N88: =(N$1=$G88)*$E88 -> 0 | O88: =(O$1=$G88)*$E88 -> 0 | P88: =(P$1=$G88)*$E88 -> 0 | Q88: =(Q$1=$G88)*$E88 -> 0 | ... GG88: =(GG$1=$G88)*$E88 -> 0
D89: 10 | E89: ='Project Inputs'!E202*(D89>0) -> 6 | G89: =(G61+'Project Inputs'!$E$186)*(D89>0) -> 48 | J89: =(J$1=$G89)*$E89 -> 0 | K89: =(K$1=$G89)*$E89 -> 0 | L89: =(L$1=$G89)*$E89 -> 0 | M89: =(M$1=$G89)*$E89 -> 0 | N89: =(N$1=$G89)*$E89 -> 0 | O89: =(O$1=$G89)*$E89 -> 0 | P89: =(P$1=$G89)*$E89 -> 0 | Q89: =(Q$1=$G89)*$E89 -> 0 | ... GG89: =(GG$1=$G89)*$E89 -> 0
D90: 11 | E90: ='Project Inputs'!E203*(D90>0) -> 6 | G90: =(G62+'Project Inputs'!$E$186)*(D90>0) -> 51 | J90: =(J$1=$G90)*$E90 -> 0 | K90: =(K$1=$G90)*$E90 -> 0 | L90: =(L$1=$G90)*$E90 -> 0 | M90: =(M$1=$G90)*$E90 -> 0 | N90: =(N$1=$G90)*$E90 -> 0 | O90: =(O$1=$G90)*$E90 -> 0 | P90: =(P$1=$G90)*$E90 -> 0 | Q90: =(Q$1=$G90)*$E90 -> 0 | ... GG90: =(GG$1=$G90)*$E90 -> 0
D91: 12 | E91: ='Project Inputs'!E204*(D91>0) -> 6 | G91: =(G63+'Project Inputs'!$E$186)*(D91>0) -> 54 | J91: =(J$1=$G91)*$E91 -> 0 | K91: =(K$1=$G91)*$E91 -> 0 | L91: =(L$1=$G91)*$E91 -> 0 | M91: =(M$1=$G91)*$E91 -> 0 | N91: =(N$1=$G91)*$E91 -> 0 | O91: =(O$1=$G91)*$E91 -> 0 | P91: =(P$1=$G91)*$E91 -> 0 | Q91: =(Q$1=$G91)*$E91 -> 0 | ... GG91: =(GG$1=$G91)*$E91 -> 0
D92: 13 | E92: ='Project Inputs'!E205*(D92>0) -> 6 | G92: =(G64+'Project Inputs'!$E$186)*(D92>0) -> 57 | J92: =(J$1=$G92)*$E92 -> 0 | K92: =(K$1=$G92)*$E92 -> 0 | L92: =(L$1=$G92)*$E92 -> 0 | M92: =(M$1=$G92)*$E92 -> 0 | N92: =(N$1=$G92)*$E92 -> 0 | O92: =(O$1=$G92)*$E92 -> 0 | P92: =(P$1=$G92)*$E92 -> 0 | Q92: =(Q$1=$G92)*$E92 -> 0 | ... GG92: =(GG$1=$G92)*$E92 -> 0
... D97: 18 | E97: ='Project Inputs'!E210*(D97>0) -> 3 | G97: =(G69+'Project Inputs'!$E$186)*(D97>0) -> 72 | J97: =(J$1=$G97)*$E97 -> 0 | K97: =(K$1=$G97)*$E97 -> 0 | L97: =(L$1=$G97)*$E97 -> 0 | M97: =(M$1=$G97)*$E97 -> 0 | N97: =(N$1=$G97)*$E97 -> 0 | O97: =(O$1=$G97)*$E97 -> 0 | P97: =(P$1=$G97)*$E97 -> 0 | Q97: =(Q$1=$G97)*$E97 -> 0 | ... GG97: =(GG$1=$G97)*$E97 -> 0
E98: ='Project Inputs'!E211*(D98>0) -> 0 | G98: =(G70+'Project Inputs'!$E$186)*(D98>0) -> 0 | J98: =(J$1=$G98)*$E98 -> 0 | K98: =(K$1=$G98)*$E98 -> 0 | L98: =(L$1=$G98)*$E98 -> 0 | M98: =(M$1=$G98)*$E98 -> 0 | N98: =(N$1=$G98)*$E98 -> 0 | O98: =(O$1=$G98)*$E98 -> 0 | P98: =(P$1=$G98)*$E98 -> 0 | Q98: =(Q$1=$G98)*$E98 -> 0 | ... GG98: =(GG$1=$G98)*$E98 -> 0
E99: ='Project Inputs'!E212*(D99>0) -> 0 | G99: =(G71+'Project Inputs'!$E$186)*(D99>0) -> 0 | J99: =(J$1=$G99)*$E99 -> 0 | K99: =(K$1=$G99)*$E99 -> 0 | L99: =(L$1=$G99)*$E99 -> 0 | M99: =(M$1=$G99)*$E99 -> 0 | N99: =(N$1=$G99)*$E99 -> 0 | O99: =(O$1=$G99)*$E99 -> 0 | P99: =(P$1=$G99)*$E99 -> 0 | Q99: =(Q$1=$G99)*$E99 -> 0 | ... GG99: =(GG$1=$G99)*$E99 -> 0
E100: ='Project Inputs'!E213*(D100>0) -> 0 | G100: =(G72+'Project Inputs'!$E$186)*(D100>0) -> 0 | J100: =(J$1=$G100)*$E100 -> 0 | K100: =(K$1=$G100)*$E100 -> 0 | L100: =(L$1=$G100)*$E100 -> 0 | M100: =(M$1=$G100)*$E100 -> 0 | N100: =(N$1=$G100)*$E100 -> 0 | O100: =(O$1=$G100)*$E100 -> 0 | P100: =(P$1=$G100)*$E100 -> 0 | Q100: =(Q$1=$G100)*$E100 -> 0 | ... GG100: =(GG$1=$G100)*$E100 -> 0
E101: ='Project Inputs'!E214*(D101>0) -> 0 | G101: =(G73+'Project Inputs'!$E$186)*(D101>0) -> 0 | J101: =(J$1=$G101)*$E101 -> 0 | K101: =(K$1=$G101)*$E101 -> 0 | L101: =(L$1=$G101)*$E101 -> 0 | M101: =(M$1=$G101)*$E101 -> 0 | N101: =(N$1=$G101)*$E101 -> 0 | O101: =(O$1=$G101)*$E101 -> 0 | P101: =(P$1=$G101)*$E101 -> 0 | Q101: =(Q$1=$G101)*$E101 -> 0 | ... GG101: =(GG$1=$G101)*$E101 -> 0
E102: ='Project Inputs'!E215*(D102>0) -> 0 | G102: =(G74+'Project Inputs'!$E$186)*(D102>0) -> 0 | J102: =(J$1=$G102)*$E102 -> 0 | K102: =(K$1=$G102)*$E102 -> 0 | L102: =(L$1=$G102)*$E102 -> 0 | M102: =(M$1=$G102)*$E102 -> 0 | N102: =(N$1=$G102)*$E102 -> 0 | O102: =(O$1=$G102)*$E102 -> 0 | P102: =(P$1=$G102)*$E102 -> 0 | Q102: =(Q$1=$G102)*$E102 -> 0 | ... GG102: =(GG$1=$G102)*$E102 -> 0
E103: ='Project Inputs'!E216*(D103>0) -> 0 | G103: =(G75+'Project Inputs'!$E$186)*(D103>0) -> 0 | J103: =(J$1=$G103)*$E103 -> 0 | K103: =(K$1=$G103)*$E103 -> 0 | L103: =(L$1=$G103)*$E103 -> 0 | M103: =(M$1=$G103)*$E103 -> 0 | N103: =(N$1=$G103)*$E103 -> 0 | O103: =(O$1=$G103)*$E103 -> 0 | P103: =(P$1=$G103)*$E103 -> 0 | Q103: =(Q$1=$G103)*$E103 -> 0 | ... GG103: =(GG$1=$G103)*$E103 -> 0
E104: ='Project Inputs'!E217*(D104>0) -> 0 | G104: =(G76+'Project Inputs'!$E$186)*(D104>0) -> 0 | J104: =(J$1=$G104)*$E104 -> 0 | K104: =(K$1=$G104)*$E104 -> 0 | L104: =(L$1=$G104)*$E104 -> 0 | M104: =(M$1=$G104)*$E104 -> 0 | N104: =(N$1=$G104)*$E104 -> 0 | O104: =(O$1=$G104)*$E104 -> 0 | P104: =(P$1=$G104)*$E104 -> 0 | Q104: =(Q$1=$G104)*$E104 -> 0 | ... GG104: =(GG$1=$G104)*$E104 -> 0
J105: =SUM(J80:J104) -> 0 | K105: =SUM(K80:K104) -> 0 | L105: =SUM(L80:L104) -> 0 | M105: =SUM(M80:M104) -> 0 | N105: =SUM(N80:N104) -> 0 | O105: =SUM(O80:O104) -> 0 | P105: =SUM(P80:P104) -> 0 | Q105: =SUM(Q80:Q104) -> 0 | ... GG105: =SUM(GG80:GG104) -> 0
B108: DEVELOPMENT
C110: Development Cashflows | E110: Costs / Ref | G110: Commencement | H110: Duration
D111: Land | E111: =IF(Output!$E$9='Model Inputs'!$E$73,-'Project Inputs'!$F$10,0) -> 0 | G111: ='Project Inputs'!E221 -> 1 | H111: ='Project Inputs'!F221 -> 1 | J111: =AND(J$1>=$G111,J$1<SUM($G111:$H111))*($E111/$H111) -> 0 | K111: =AND(K$1>=$G111,K$1<SUM($G111:$H111))*($E111/$H111) -> 0 | L111: =AND(L$1>=$G111,L$1<SUM($G111:$H111))*($E111/$H111) -> 0 | M111: =AND(M$1>=$G111,M$1<SUM($G111:$H111))*($E111/$H111) -> 0 | N111: =AND(N$1>=$G111,N$1<SUM($G111:$H111))*($E111/$H111) -> 0 | O111: =AND(O$1>=$G111,O$1<SUM($G111:$H111))*($E111/$H111) -> 0 | P111: =AND(P$1>=$G111,P$1<SUM($G111:$H111))*($E111/$H111) -> 0 | Q111: =AND(Q$1>=$G111,Q$1<SUM($G111:$H111))*($E111/$H111) -> 0 | ... GG111: =AND(GG$1>=$G111,GG$1<SUM($G111:$H111))*($E111/$H111) -> 0
D112: Ground Lease | E112: =IF(Output!$E$9='Model Inputs'!$F$73,-'Project Inputs'!$E$15,0) -> -56475.35 | G112: Spread through development phase | J112: =$E$112*J$3 -> -56475.35 | K112: =$E$112*K$3 -> -56475.35 | L112: =$E$112*L$3 -> -56475.35 | M112: =$E$112*M$3 -> -56475.35 | N112: =$E$112*N$3 -> -56475.35 | O112: =$E$112*O$3 -> -56475.35 | P112: =$E$112*P$3 -> -56475.35 | Q112: =$E$112*Q$3 -> -56475.35 | ... GG112: =$E$112*GG$3 -> 0
D113: Preliminary Costs | E113: =-'Project Inputs'!H148 -> -4022500 | G113: ='Project Inputs'!E222 -> 2 | H113: ='Project Inputs'!F222 -> 4 | J113: =AND(J$1>=$G113,J$1<SUM($G113:$H113))*($E113/$H113) -> 0 | K113: =AND(K$1>=$G113,K$1<SUM($G113:$H113))*($E113/$H113) -> -1005625 | L113: =AND(L$1>=$G113,L$1<SUM($G113:$H113))*($E113/$H113) -> -1005625 | M113: =AND(M$1>=$G113,M$1<SUM($G113:$H113))*($E113/$H113) -> -1005625 | N113: =AND(N$1>=$G113,N$1<SUM($G113:$H113))*($E113/$H113) -> -1005625 | O113: =AND(O$1>=$G113,O$1<SUM($G113:$H113))*($E113/$H113) -> 0 | P113: =AND(P$1>=$G113,P$1<SUM($G113:$H113))*($E113/$H113) -> 0 | Q113: =AND(Q$1>=$G113,Q$1<SUM($G113:$H113))*($E113/$H113) -> 0 | ... GG113: =AND(GG$1>=$G113,GG$1<SUM($G113:$H113))*($E113/$H113) -> 0
D114: Land Development | E114: =-'Project Inputs'!I79 -> -13248789 | G114: Refer timing above | J114: =J$21*$E114 -> 0 | K114: =K$21*$E114 -> 0 | L114: =L$21*$E114 -> 0 | M114: =M$21*$E114 -> 0 | N114: =N$21*$E114 -> 0 | O114: =O$21*$E114 -> -662439.45 | P114: =P$21*$E114 -> -662439.45 | Q114: =Q$21*$E114 -> -662439.45 | ... GG114: =GG$21*$E114 -> 0
D115: Vertical Construction | E115: =-'Project Inputs'!G55 -> -47818832 | G115: Refer timing above | J115: =J49/SUM($H$24:$H$48)*$E$115 -> 0 | K115: =K49/SUM($H$24:$H$48)*$E$115 -> 0 | L115: =L49/SUM($H$24:$H$48)*$E$115 -> 0 | M115: =M49/SUM($H$24:$H$48)*$E$115 -> 0 | N115: =N49/SUM($H$24:$H$48)*$E$115 -> 0 | O115: =O49/SUM($H$24:$H$48)*$E$115 -> 0 | P115: =P49/SUM($H$24:$H$48)*$E$115 -> 0 | Q115: =Q49/SUM($H$24:$H$48)*$E$115 -> 0 | ... GG115: =GG49/SUM($H$24:$H$48)*$E$115 -> 0
D116: Community Centre | E116: =-'Project Inputs'!H123 -> -7662197.7 | G116: ='Project Inputs'!E223 -> 24 | H116: ='Project Inputs'!F223 -> 9 | J116: =AND(J$1>=$G116,J$1<SUM($G116:$H116))*($E116/$H116) -> 0 | K116: =AND(K$1>=$G116,K$1<SUM($G116:$H116))*($E116/$H116) -> 0 | L116: =AND(L$1>=$G116,L$1<SUM($G116:$H116))*($E116/$H116) -> 0 | M116: =AND(M$1>=$G116,M$1<SUM($G116:$H116))*($E116/$H116) -> 0 | N116: =AND(N$1>=$G116,N$1<SUM($G116:$H116))*($E116/$H116) -> 0 | O116: =AND(O$1>=$G116,O$1<SUM($G116:$H116))*($E116/$H116) -> 0 | P116: =AND(P$1>=$G116,P$1<SUM($G116:$H116))*($E116/$H116) -> 0 | Q116: =AND(Q$1>=$G116,Q$1<SUM($G116:$H116))*($E116/$H116) -> 0 | ... GG116: =AND(GG$1>=$G116,GG$1<SUM($G116:$H116))*($E116/$H116) -> 0
D117: Holding & Other | E117: =-'Project Inputs'!H159 -> -2491725 | G117: Spread through development phase | J117: =$E117/SUM($J$3:$DW$3)*J$3 -> -36111.957 | K117: =$E117/SUM($J$3:$DW$3)*K$3 -> -36111.957 | L117: =$E117/SUM($J$3:$DW$3)*L$3 -> -36111.957 | M117: =$E117/SUM($J$3:$DW$3)*M$3 -> -36111.957 | N117: =$E117/SUM($J$3:$DW$3)*N$3 -> -36111.957 | O117: =$E117/SUM($J$3:$DW$3)*O$3 -> -36111.957 | P117: =$E117/SUM($J$3:$DW$3)*P$3 -> -36111.957 | Q117: =$E117/SUM($J$3:$DW$3)*Q$3 -> -36111.957 | ... GG117: =$E117/SUM($J$3:$DW$3)*GG$3 -> 0
D118: KPV Processing Fee | E118: ='Project Inputs'!E166 -> 0.015 | G118: Linked to other costs | J118: =SUM(J113,J114,J115,J116,J117)*$E$118 -> -541.67935 | K118: =SUM(K113,K114,K115,K116,K117)*$E$118 -> -15626.054 | L118: =SUM(L113,L114,L115,L116,L117)*$E$118 -> -15626.054 | M118: =SUM(M113,M114,M115,M116,M117)*$E$118 -> -15626.054 | N118: =SUM(N113,N114,N115,N116,N117)*$E$118 -> -15626.054 | O118: =SUM(O113,O114,O115,O116,O117)*$E$118 -> -10478.271 | P118: =SUM(P113,P114,P115,P116,P117)*$E$118 -> -10478.271 | Q118: =SUM(Q113,Q114,Q115,Q116,Q117)*$E$118 -> -10478.271 | ... GG118: =SUM(GG113,GG114,GG115,GG116,GG117)*$E$118 -> 0
D119: KPV Transaction Fee | E119: ='Project Inputs'!E165*SUM(E113,E114,E115,E116,E117,-'Project Inputs'!F10) -> -865391.14 | G119: ='Project Inputs'!E224 -> 1 | H119: ='Project Inputs'!F224 -> 1 | J119: =AND(J$1>=$G119,J$1<SUM($G119:$H119))*($E119/$H119) -> -865391.14 | K119: =AND(K$1>=$G119,K$1<SUM($G119:$H119))*($E119/$H119) -> 0 | L119: =AND(L$1>=$G119,L$1<SUM($G119:$H119))*($E119/$H119) -> 0 | M119: =AND(M$1>=$G119,M$1<SUM($G119:$H119))*($E119/$H119) -> 0 | N119: =AND(N$1>=$G119,N$1<SUM($G119:$H119))*($E119/$H119) -> 0 | O119: =AND(O$1>=$G119,O$1<SUM($G119:$H119))*($E119/$H119) -> 0 | P119: =AND(P$1>=$G119,P$1<SUM($G119:$H119))*($E119/$H119) -> 0 | Q119: =AND(Q$1>=$G119,Q$1<SUM($G119:$H119))*($E119/$H119) -> 0 | ... GG119: =AND(GG$1>=$G119,GG$1<SUM($G119:$H119))*($E119/$H119) -> 0
D120: KPV Management Fee | E120: =-SUM('Project Inputs'!E167:E168) -> -300000 | F120: p.a. | G120: Spread through development phase | J120: =$E120*J$3/Periodicity -> -25000 | K120: =$E120*K$3/Periodicity -> -25000 | L120: =$E120*L$3/Periodicity -> -25000 | M120: =$E120*M$3/Periodicity -> -25000 | N120: =$E120*N$3/Periodicity -> -25000 | O120: =$E120*O$3/Periodicity -> -25000 | P120: =$E120*P$3/Periodicity -> -25000 | Q120: =$E120*Q$3/Periodicity -> -25000 | ... GG120: =$E120*GG$3/Periodicity -> 0
D121: Inflation - Cost | G121: Refer inflation factors | J121: =SUM(J113:J120)*(J$9-1) -> 0 | K121: =SUM(K113:K120)*(K$9-1) -> 0 | L121: =SUM(L113:L120)*(L$9-1) -> 0 | M121: =SUM(M113:M120)*(M$9-1) -> 0 | N121: =SUM(N113:N120)*(N$9-1) -> 0 | O121: =SUM(O113:O120)*(O$9-1) -> 0 | P121: =SUM(P113:P120)*(P$9-1) -> 0 | Q121: =SUM(Q113:Q120)*(Q$9-1) -> 0 | ... GG121: =SUM(GG113:GG120)*(GG$9-1) -> 0
D122: Preferred Interest | G122: Refer calculations below | J122: =SUM(J147:J148) -> 0 | K122: =SUM(K147:K148) -> -3688.2005 | L122: =SUM(L147:L148) -> -7983.4323 | M122: =SUM(M147:M148) -> -12307.299 | N122: =SUM(N147:N148) -> -16659.992 | O122: =SUM(O147:O148) -> -21041.702 | P122: =SUM(P147:P148) -> -24146.374 | Q122: =SUM(Q147:Q148) -> -27271.744 | ... GG122: =SUM(GG147:GG148) -> 0
...

Sheet Output
B2: KEY INPUTS & SENSITIVITY
C4: A Class Share Allocation
D5: Hāpai | E5: ='Model Inputs'!E17 -> 1 | F5: % of A-class shares
D6: ='Model Inputs'!D18 -> Vendor | E6: 0 | F6: % of A-class shares
C8: Land
D9: Model | E9: Operating Lease | F9: "Ownership" covers both freehold and pre-paid ground lease
E11: Per sqm | F11: Total
D12: Value (excl GST) | E12: 200 | F12: =E12*'Project Inputs'!$E$6 -> 9821800
D13: Value (incl GST) | E13: =E12*1.15 -> 230 | F13: =E13*'Project Inputs'!$E$6 -> 11295070
D15: Cap Rate | E15: ='Project Inputs'!E13 -> 0.06 | F15: only applicable to ground lease model
D16: Rental - annual (incl GST) | E16: =E15*F13 -> 677704.2
C18: Build Cost
D19: Input Build Rate (psm) (incl GST) | E19: ='Project Inputs'!E48 -> 3718.6475 | F19: base build rate (with premium applied for apartments where applicable)
C21: ORA Sales | I21: Area m2 | J21: m2 Sell
D22: Base Value 2 Bedroom Units | E22: ='Project Inputs'!E41 -> 975000 | I22: 122 | J22: =E22/122 -> 7991.8033
D23: Base Value 3 Bedroom Units | E23: ='Project Inputs'!E42 -> 1100000 | F23: all units valued in proportion to base value | I23: 144 | J23: =E23/144 -> 7638.8889
D24: Average Value (incl GST) | E24: ='Project Inputs'!L38 -> 982142.86 | F24: average will vary based on proposed delivery mix
C26: Growth & Inflation
D27: Capital Growth | E27: ='Model Inputs'!E66 -> 0.02 | F27: applicable to ORA sales and unit turnover income
D28: Inflation - Costs | E28: ='Model Inputs'!E67 -> 0.02 | F28: applicable to development costs
D29: Inflation - Lease | E29: ='Model Inputs'!E68 -> 0.02 | F29: applicable to operating lease
B32: ORA SURPLUS
D34: ORA Sales | E34: =SUM(Cashflow!J125:GG125)/1000 -> 103125
D35: Inflation - ORA | E35: =SUM(Cashflow!J126:GG126)/1000 -> 6720.4703 | F35: increase in values during development - highlighted as separate item for transparency
E36: =SUM(E34:E35) -> 109845.47
D38: Land | E38: =SUM(Cashflow!J111:GG111)/-1000 -> 0
D39: Ground Lease | E39: =SUM(Cashflow!J112:GG112)/-1000 -> 3896.7992
D40: Preliminary Costs | E40: =SUM(Cashflow!J113:GG113)/-1000 -> 4022.5
D41: Land Development | E41: =SUM(Cashflow!J114:GG114)/-1000 -> 13248.789
D42: Vertical Construction | E42: =SUM(Cashflow!J115:GG115)/-1000 -> 47818.832
D43: Community Centre | E43: =SUM(Cashflow!J116:GG116)/-1000 -> 7662.1977
D44: Holding & Other | E44: =SUM(Cashflow!J117:GG117)/-1000 -> 2491.725
D45: KPV Processing Fee | E45: =SUM(Cashflow!J118:GG118)/-1000 -> 1128.6607
D46: KPV Transaction Fee | E46: =SUM(Cashflow!J119:GG119)/-1000 -> 865.39114
D47: KPV Management Fee | E47: =SUM(Cashflow!J120:GG120)/-1000 -> 1725
D48: Inflation - Cost | E48: =SUM(Cashflow!J121:GG121)/-1000 -> 3751.1493 | F48: cost inflation during development - highlighted as separate item for transparency
E49: =SUM(E38:E48) -> 86611.044
D51: Surplus Pre-Preferred | E51: =E36-E49 -> 23234.426 | F51: =E51/$E$34 -> 0.22530353
D53: Preferred Interest | E53: =SUM(Cashflow!J122:CC122)/-1000 -> 5250.6435 | F53: in 6 Years of Development | K53: Preferred Interest; Ownership | M53: 11251.331 | N53: Copy and paste for lease ORA surplus scenario
K54: Preferred Interest: Formula Driven | M54: =SUM(Cashflow!J122:GG122)/-1000 -> 5250.6435 | N54: For comparison/to maintain back up
D55: ORA Surplus | E55: =E51-E53 -> 17983.783 | F55: =E55/$E$34 -> 0.17438819 | G55: easy dev margin indicator
J56: Noting that at 50/50 investment the ORA surplus shifts directly from KPV to the Vendor as part of entering the lease
B58: OUTPUT
E60: Hāpai | F60: KPV | G60: ='Model Inputs'!D18 -> Vendor | H60: Total | J60: A Class | K60: B Class
D61: Shareholdings
D62: A-Class | E62: ='Model Inputs'!E26 -> 0.7 | F62: ='Model Inputs'!F26 -> 0 | G62: ='Model Inputs'!G26 -> 0 | H62: ='Model Inputs'!H26 -> 0.7 | J62: ='Model Inputs'!H26 -> 0.7 | K62: 0
D63: B-Class | E63: ='Model Inputs'!E27 -> 0.15 | F63: ='Model Inputs'!F27 -> 0.15 | G63: ='Model Inputs'!G27 -> 0 | H63: ='Model Inputs'!H27 -> 0.3 | J63: 0 | K63: ='Model Inputs'!H27 -> 0.3
D64: Total | E64: =SUM(E62:E63) -> 0.85 | F64: =SUM(F62:F63) -> 0.15 | G64: =SUM(G62:G63) -> 0 | H64: =SUM(H62:H63) -> 1 | J64: =SUM(J62:J63) -> 0.7 | K64: =SUM(K62:K63) -> 0.3
D66: Development Output
D67: Peak Capital (net of preferred) | E67: =E62/$H$62*$H$67 -> 20603.539 | F67: =F62/$H$62*$H$67 -> 0 | G67: =G62/$H$62*$H$67 -> 0 | H67: =-MIN(Cashflow!J222:GG222)/1000 -> 20603.539 | J67: =J62/$H$62*$H$67 -> 20603.539 | K67: =K62/$H$62*$H$67 -> 0
D69: Share of ORA Surplus | E69: =E64*$E$55 -> 15286.215 | F69: =F64*$E$55 -> 2697.5674 | G69: =G64*$E$55 -> 0 | H69: =H64*$E$55 -> 17983.783 | J69: =J64*$E$55 -> 12588.648 | K69: =K64*$E$55 -> 5395.1348
D70: Share of Preferred Interest | E70: =E62/$H$62*$E$53 -> 5250.6435 | F70: =F62/$H$62*$E$53 -> 0 | G70: =G62/$H$62*$E$53 -> 0 | H70: =H62/$H$62*$E$53 -> 5250.6435 | J70: =J62/$H$62*$E$53 -> 5250.6435 | K70: =K62/$H$62*$E$53 -> 0
D71: Total | E71: =SUM(E69:E70) -> 20536.859 | F71: =SUM(F69:F70) -> 2697.5674 | G71: =SUM(G69:G70) -> 0 | H71: =SUM(H69:H70) -> 23234.426 | J71: =SUM(J69:J70) -> 17839.291 | K71: =SUM(K69:K70) -> 5395.1348
D73: Margin (on share of costs) | E73: =IF(E$62>0,(E$71/($E$49*E$62/$H$62)),"n/a") -> 0.23711593 | F73: =IF(F$62>0,(F$71/($E$49*F$62/$H$62)),"n/a") -> n/a | G73: =IF(G$62>0,(G$71/($E$49*G$62/$H$62)),"n/a") -> n/a | H73: =IF(H$62>0,(H$71/($E$49*H$62/$H$62)),"n/a") -> 0.2682617 | J73: =IF(J$62>0,(J$71/($E$49*J$62/$H$62)),"n/a") -> 0.20597017 | K73: =IF(K$62>0,(K$71/($E$49*K$62/$H$62)),"n/a") -> n/a
D74: Margin (on share of capital) | E74: =IF(E$62>0,(E71/E67),"n/a") -> 0.99676362 | F74: =IF(F$62>0,(F71/F67),"n/a") -> n/a | G74: =IF(G$62>0,(G71/G67),"n/a") -> n/a | H74: =IF(H$62>0,(H$71/($H$67)),"n/a") -> 1.127691 | J74: =IF(J$62>0,(J$71/($H$67)),"n/a") -> 0.86583625 | K74: =IF(K$62>0,(K$71/($E$67*K$62/$H$62)),"n/a") -> n/a
D77: Long Term Investment
D78: IRR (15 year - real basis) | E78: =IF(E$62>0,XIRR(Cashflow!$J$197:$GG$197,Cashflow!$J$2:$GG$2),"n/a") -> 0.20309383 | F78: =IF(F$62>0,XIRR(Cashflow!$J$202:$GG$202,Cashflow!$J$2:$GG$2),"n/a") -> n/a | G78: =IF(G$62>0,XIRR(Cashflow!$J$207:$GG$207,Cashflow!$J$2:$GG$2),"n/a") -> n/a | H78: =IF(H$62>0,XIRR(Cashflow!$J$213:$GG$213,Cashflow!$J$2:$GG$2),"n/a") -> 0.21641291 | J78: =XIRR(Cashflow!$J$183:$GG$183,Cashflow!$J$2:$GG$2) -> 0.18860542 | K78: =XIRR(Cashflow!$J$189:$GG$189,Cashflow!$J$2:$GG$2) -> 2.9802322e-09
D80: Annual Cashflow (at maturity) | E80: =$H80*E$64 -> 2565.1573 | F80: =$H80*F$64 -> 452.67481 | G80: =$H80*G$64 -> 0 | H80: =SUM(Cashflow!GG147:GG148,Cashflow!GG170:GG171)*12/1000 -> 3017.8321 | J80: =$H80*J$64 -> 2112.4824 | K80: =$H80*K$64 -> 905.34962 | L80: Note it will take 4-5 years post development for the village to reach maturity (i.e. full churn / turnover)
D82: Investment Value (at maturity) | E82: =$H82*E$64 -> 14658.041 | F82: =$H82*F$64 -> 2586.7132 | G82: =$H82*G$64 -> 0 | H82: =SUM(Cashflow!GG172,Cashflow!GG151)/1000 -> 17244.755 | J82: =$H82*J$64 -> 12071.328 | K82: =$H82*K$64 -> 5173.4264 | L82: Operator's Interest (including ground lease if appplicable)

Sheet Village Valuation
B2: VILLAGE VALUATION ON COMPLETION
B6: VILLAGE OVERVIEW
B8: Village Characteristics | E8: Value | F8: Notes
B9: Total Units | E9: 105 | F9: Independent living units
B10: Land Area (sqm) | E10: ='Project Inputs'!E6 -> 49109 | F10: Total site area
B11: Village Star Rating | E11: ='Project Inputs'!E103 -> 4.5
B12: Community Centre (sqm) | E12: 925 | F12: Pool, gym, dining, games, admin
B13: Average Resident Tenure | E13: ='Model Inputs'!E39 -> 8
B14: Deferred Management Fee (DMF) | E14: ='Model Inputs'!E40 -> 0.24
B15: Resale Fee | E15: ='Model Inputs'!E41 -> 0.01
B17: Unit Mix Summary | D17: Typology | E17: Qty | F17: ORA Value | G17: Total Value
B18: BSG — 2 Bed Duplex (SG) | D18: House | E18: 50 | F18: ='Project Inputs'!E41 -> 975000 | G18: =E18*F18 -> 48750000
B19: MNSG — 3 Bed Duplex (SG) | D19: House | E19: 30 | F19: ='Project Inputs'!E42 -> 1100000 | G19: =E19*F19 -> 33000000
B20: R6 — 1 Bed (Six-Unit Block) | D20: House | E20: 20 | F20: 750000 | G20: =E20*F20 -> 15000000
B21: Total / Weighted Average | E21: =SUM(E18:E20) -> 100 | F21: =G21/E21 -> 967500 | G21: =SUM(G18:G20) -> 96750000
B23: TOTAL DEVELOPMENT COST
B25: Development Cost Build-Up | E25: $000s | F25: % of Total | G25: $/Unit
B26: Land (incl GST) | E26: =Output!F13/1000 -> 11295.07 | F26: =E26/$E$36 -> 0.11536634 | G26: =E26*1000/E21 -> 112950.7
B27: Ground Lease (development period) | E27: =Output!E39 -> 3896.7992 | F27: =E27/$E$36 -> 0.039801387 | G27: =E27*1000/E21 -> 38967.992
B28: Preliminary Costs | E28: =Output!E40 -> 4022.5 | F28: =E28/$E$36 -> 0.041085279 | G28: =E28*1000/E21 -> 40225
B29: Land Development | E29: =Output!E41 -> 13248.789 | F29: =E29/$E$36 -> 0.13532136 | G29: =E29*1000/E21 -> 132487.89
B30: Vertical Construction | E30: =Output!E42 -> 47818.832 | F30: =E30/$E$36 -> 0.48841518 | G30: =E30*1000/E21 -> 478188.32
B31: Community Centre | E31: =Output!E43 -> 7662.1977 | F31: =E31/$E$36 -> 0.078260666 | G31: =E31*1000/E21 -> 76621.977
B32: Holding & Other Costs | E32: =Output!E44 -> 2491.725 | F32: =E32/$E$36 -> 0.025450147 | G32: =E32*1000/E21 -> 24917.25
B33: KPV Fees (Processing + Transaction + Mgmt) | E33: =Output!E45+Output!E46+Output!E47 -> 3719.0518 | F33: =E33/$E$36 -> 0.037985899 | G33: =E33*1000/E21 -> 37190.518
B34: Cost Inflation (during development) | E34: =Output!E48 -> 3751.1493 | F34: =E34/$E$36 -> 0.038313739 | G34: =E34*1000/E21 -> 37511.493
B36: Total Development Cost | E36: =SUM(E26:E34) -> 97906.114 | F36: =E36/$E$36 -> 1 | G36: =E36*1000/E21 -> 979061.14
B38: INCOME APPROACH — DISCOUNTED CASH FLOW
B40: Valuation Assumptions | E40: Assumption | F40: Source / Notes
B41: Average ORA Value (Day 1) | E41: =F21 -> 967500 | F41: Weighted average across unit mix
B42: Total ORA Portfolio Value (Day 1, $000s) | E42: =G21/1000 -> 96750 | F42: 100 units × average ORA
B43: Capital Growth Rate (p.a.) | E43: ='Model Inputs'!E66 -> 0.02 | F43: Applied to ORA values and turnover income
B44: Average Resident Tenure | E44: =E13 -> 8 | F44: Implies ~12.5% annual unit turnover at maturity
B45: DMF Retained on Turnover | E45: =E14 -> 0.24 | F45: Deferred management fee
B46: Resale Commission | E46: =E15 -> 0.01 | F46: Agent / marketing fee on resale
B47: Net Margin on Turnover | E47: =E45-E46 -> 0.23 | F47: DMF less resale costs = net operator margin
B48: Discount Rate (Terminal Value) | E48: ='Model Inputs'!E61 -> 0.175 | F48: Applied to capitalise stabilised cashflows
B50: Stabilised Annual Income ($000s) | E50: $000s | F50: Notes
B51: Unit Turnover Income (at maturity) | E51: =Output!H80-Cashflow!GG171*12/1000 -> 3912.0484 | F51: DMF income from unit resales at full churn
B52: Less: Ground Lease Rental | E52: =Cashflow!GG171*12/1000 -> -894.2163 | F52: Annual lease cost (if operating lease model)
B53: Net Annual Operating Income | E53: =Output!H80 -> 3017.8321 | F53: From Cashflow model at stabilisation (Yr 15)
B55: VALUATION OF OPERATOR'S INTEREST (On Completion) | E55: $000s | F55: Notes
B57: A. Capitalisation of Stabilised Income
B58: Net Annual Operating Income ($000s) | E58: =E53 -> 3017.8321 | F58: Stabilised net income per cashflow model
B59: Capitalisation Rate | E59: =E48 -> 0.175 | F59: Terminal discount rate (CBRE/JLL range: 13–18%)
B60: Capitalised Value of Operating Income | E60: =E58/E59 -> 17244.755 | F60: = Net Income ÷ Cap Rate
B62: B. Underlying ORA Portfolio Value
B63: Total ORA Value (Day 1, $000s) | E63: =E42 -> 96750 | F63: Sum of all unit ORAs at completion
B65: C. Development Surplus
B66: Total ORA Revenue ($000s) | E66: =Output!E34+Output!E35 -> 109845.47 | F66: Including value growth during development
B67: Less: Total Development Expenditure ($000s) | E67: =-Output!E49 -> -86611.044 | F67: All-in cost (land, construction, fees, inflation)
B68: Surplus Pre-Preferred ($000s) | E68: =E66+E67 -> 23234.426 | F68: Per Output sheet
B69: Less: Preferred Interest ($000s) | E69: =-Output!E53 -> -5250.6435 | F69: Accrued preferred return to A-class investors
B70: Net ORA Surplus | E70: =E68+E69 -> 17983.783 | F70: Distributable surplus from development
B71: Development Margin (on ORA revenue) | E71: =E70/E66 -> 0.16371893 | F71: ORA surplus as % of total ORA revenue
B73: MARKET COMPARISON — COMPARABLE TRANSACTIONS
B75: NZ Retirement Village Valuation Benchmarks (CBRE / JLL) | E75: Low | F75: Mid | G75: High | H75: This Village | I75: Notes
B76: Discount Rate (Terminal Cap Rate) | E76: 0.13 | F76: 0.155 | G76: 0.18 | H76: =E48 -> 0.175 | I76: CBRE/JLL range for NZ villages
B77: DMF Rate | E77: 0.2 | F77: 0.25 | G77: 0.3 | H77: =E45 -> 0.24 | I77: Standard NZ market range
B78: Average Tenure (years) | E78: 7 | F78: 8 | G78: 10 | H78: =E44 -> 8 | I78: Typical NZ village tenure
B79: Capital Growth Rate | E79: 0.02 | F79: 0.03 | G79: 0.04 | H79: =E43 -> 0.02 | I79: Long-term NZ property CG
B80: Value per Unit (Operator's Interest) | E80: 100000 | F80: 135000 | G80: 175000 | H80: =E60*1000/E21 -> 172447.55 | I80: Per-unit value of operator's interest
B82: Implied Valuation ($000s)
B83: Per-Unit Basis | E83: =E80*E21/1000 -> 10000 | F83: =F80*E21/1000 -> 13500 | G83: =G80*E21/1000 -> 17500 | H83: =H80*E21/1000 -> 17244.755 | I83: Total village value (operator's interest)
B84: Income Capitalisation Basis | E84: =E53/E76 -> 23214.093 | F84: =E53/F76 -> 19469.884 | G84: =E53/G76 -> 16765.734 | H84: =E60 -> 17244.755 | I84: Net income ÷ cap rate at each scenario
B86: VALUATION SUMMARY ON COMPLETION
B88: Valuation of Operator's Interest | E88: $000s | F88: Per Unit | G88: Notes
B89: Stabilised Net Operating Income ($000s p.a.) | E89: =E53 -> 3017.8321 | F89: =E89*1000/$E$21 -> 30178.321 | G89: Annual turnover income less ground lease
B90: Capitalisation Rate | E90: =E48 -> 0.175
B92: Capitalised Value (Operator's Interest) | E92: =E89/E90 -> 17244.755 | F92: =E92*1000/$E$21 -> 172447.55 | G92: = Net Income ÷ Cap Rate (DCF basis)
B94: Cross-Check: Model IRR (15 year) | E94: =Output!H78 -> 0.21641291 | G94: Per Cashflow model (whole village)
B96: Key Metrics
B97: Total Development Cost ($000s) | E97: =E36 -> 97906.114 | F97: =E97*1000/$E$21 -> 979061.14
B98: ORA Portfolio Value ($000s) | E98: =E42 -> 96750 | F98: =E98*1000/$E$21 -> 967500
B99: Net ORA Surplus ($000s) | E99: =E70 -> 17983.783 | F99: =E99*1000/$E$21 -> 179837.83
B100: Capitalised Value ($000s) | E100: =E92 -> 17244.755 | F100: =E100*1000/$E$21 -> 172447.55
B101: Total Value (ORA + Operator’s Interest, $000s) | E101: =E98+E100 -> 113994.75 | F101: =E101*1000/$E$21 -> 1139947.5
B102: Yield on Cost (Stabilised Income / Dev Cost) | E102: =E89/E97 -> 0.030823734
B103: Capitalised Value as % of ORA Portfolio | E103: =E100/E98 -> 0.17824036
B105: SENSITIVITY ANALYSIS
B107: Operator’s Interest ($000s): Discount Rate vs DMF
D108: DMF Rate → | E108: 0.2 | F108: 0.22 | G108: 0.24 | H108: 0.26 | I108: 0.28
C109: Discount | D109: 0.13 | E109: =($E$42*(E$108-$E$46)/$E$44+$E$52)/$D109 -> 10796.894 | F109: =($E$42*(F$108-$E$46)/$E$44+$E$52)/$D109 -> 12657.471 | G109: =($E$42*(G$108-$E$46)/$E$44+$E$52)/$D109 -> 14518.048 | H109: =($E$42*(H$108-$E$46)/$E$44+$E$52)/$D109 -> 16378.625 | I109: =($E$42*(I$108-$E$46)/$E$44+$E$52)/$D109 -> 18239.202
C110: Rate ↓ | D110: 0.145 | E110: =($E$42*(E$108-$E$46)/$E$44+$E$52)/$D110 -> 9679.9738 | F110: =($E$42*(F$108-$E$46)/$E$44+$E$52)/$D110 -> 11348.077 | G110: =($E$42*(G$108-$E$46)/$E$44+$E$52)/$D110 -> 13016.181 | H110: =($E$42*(H$108-$E$46)/$E$44+$E$52)/$D110 -> 14684.284 | I110: =($E$42*(I$108-$E$46)/$E$44+$E$52)/$D110 -> 16352.388
D111: 0.16 | E111: =($E$42*(E$108-$E$46)/$E$44+$E$52)/$D111 -> 8772.4763 | F111: =($E$42*(F$108-$E$46)/$E$44+$E$52)/$D111 -> 10284.195 | G111: =($E$42*(G$108-$E$46)/$E$44+$E$52)/$D111 -> 11795.914 | H111: =($E$42*(H$108-$E$46)/$E$44+$E$52)/$D111 -> 13307.633 | I111: =($E$42*(I$108-$E$46)/$E$44+$E$52)/$D111 -> 14819.351
D112: 0.175 | E112: =($E$42*(E$108-$E$46)/$E$44+$E$52)/$D112 -> 8020.5497 | F112: =($E$42*(F$108-$E$46)/$E$44+$E$52)/$D112 -> 9402.6926 | G112: =($E$42*(G$108-$E$46)/$E$44+$E$52)/$D112 -> 10784.835 | H112: =($E$42*(H$108-$E$46)/$E$44+$E$52)/$D112 -> 12166.978 | I112: =($E$42*(I$108-$E$46)/$E$44+$E$52)/$D112 -> 13549.121
D113: 0.19 | E113: =($E$42*(E$108-$E$46)/$E$44+$E$52)/$D113 -> 7387.3484 | F113: =($E$42*(F$108-$E$46)/$E$44+$E$52)/$D113 -> 8660.3747 | G113: =($E$42*(G$108-$E$46)/$E$44+$E$52)/$D113 -> 9933.4011 | H113: =($E$42*(H$108-$E$46)/$E$44+$E$52)/$D113 -> 11206.427 | I113: =($E$42*(I$108-$E$46)/$E$44+$E$52)/$D113 -> 12479.454
B115: Operator’s Interest ($000s): Discount Rate vs Capital Growth
D116: Capital Growth → | E116: 0.01 | F116: 0.015 | G116: 0.02 | H116: 0.03 | I116: 0.04
C117: Discount | D117: 0.13 | E117: =($E$42*($E$45-$E$46)*(1+E$116)^$E$44/$E$44+$E$52)/$D117 -> 16290.902 | F117: =($E$42*($E$45-$E$46)*(1+F$116)^$E$44/$E$44+$E$52)/$D117 -> 17224.563 | G117: =($E$42*($E$45-$E$46)*(1+G$116)^$E$44/$E$44+$E$52)/$D117 -> 18190.981 | H117: =($E$42*($E$45-$E$46)*(1+H$116)^$E$44/$E$44+$E$52)/$D117 -> 20226.03 | I117: =($E$42*($E$45-$E$46)*(1+I$116)^$E$44/$E$44+$E$52)/$D117 -> 22404.185
C118: Rate ↓ | D118: 0.145 | E118: =($E$42*($E$45-$E$46)*(1+E$116)^$E$44/$E$44+$E$52)/$D118 -> 14605.637 | F118: =($E$42*($E$45-$E$46)*(1+F$116)^$E$44/$E$44+$E$52)/$D118 -> 15442.712 | G118: =($E$42*($E$45-$E$46)*(1+G$116)^$E$44/$E$44+$E$52)/$D118 -> 16309.155 | H118: =($E$42*($E$45-$E$46)*(1+H$116)^$E$44/$E$44+$E$52)/$D118 -> 18133.682 | I118: =($E$42*($E$45-$E$46)*(1+I$116)^$E$44/$E$44+$E$52)/$D118 -> 20086.511
D119: 0.16 | E119: =($E$42*($E$45-$E$46)*(1+E$116)^$E$44/$E$44+$E$52)/$D119 -> 13236.358 | F119: =($E$42*($E$45-$E$46)*(1+F$116)^$E$44/$E$44+$E$52)/$D119 -> 13994.958 | G119: =($E$42*($E$45-$E$46)*(1+G$116)^$E$44/$E$44+$E$52)/$D119 -> 14780.172 | H119: =($E$42*($E$45-$E$46)*(1+H$116)^$E$44/$E$44+$E$52)/$D119 -> 16433.649 | I119: =($E$42*($E$45-$E$46)*(1+I$116)^$E$44/$E$44+$E$52)/$D119 -> 18203.4
D120: 0.175 | E120: =($E$42*($E$45-$E$46)*(1+E$116)^$E$44/$E$44+$E$52)/$D120 -> 12101.813 | F120: =($E$42*($E$45-$E$46)*(1+F$116)^$E$44/$E$44+$E$52)/$D120 -> 12795.39 | G120: =($E$42*($E$45-$E$46)*(1+G$116)^$E$44/$E$44+$E$52)/$D120 -> 13513.3 | H120: =($E$42*($E$45-$E$46)*(1+H$116)^$E$44/$E$44+$E$52)/$D120 -> 15025.051 | I120: =($E$42*($E$45-$E$46)*(1+I$116)^$E$44/$E$44+$E$52)/$D120 -> 16643.109
D121: 0.19 | E121: =($E$42*($E$45-$E$46)*(1+E$116)^$E$44/$E$44+$E$52)/$D121 -> 11146.407 | F121: =($E$42*($E$45-$E$46)*(1+F$116)^$E$44/$E$44+$E$52)/$D121 -> 11785.228 | G121: =($E$42*($E$45-$E$46)*(1+G$116)^$E$44/$E$44+$E$52)/$D121 -> 12446.461 | H121: =($E$42*($E$45-$E$46)*(1+H$116)^$E$44/$E$44+$E$52)/$D121 -> 13838.862 | I121: =($E$42*($E$45-$E$46)*(1+I$116)^$E$44/$E$44+$E$52)/$D121 -> 15329.179
B123: PARTNER VALUE ALLOCATION ON COMPLETION
B125: Shareholding Structure | E125: Hāpai | F125: KPV | G125: Vendor | H125: Total
B126: A-Class Shares | E126: =Output!E62 -> 0.7 | F126: =Output!F62 -> 0 | G126: =Output!G62 -> 0 | H126: =SUM(E126:G126) -> 0.7
B127: B-Class Shares | E127: =Output!E63 -> 0.15 | F127: =Output!F63 -> 0.15 | G127: =Output!G63 -> 0 | H127: =SUM(E127:G127) -> 0.3
B128: Total Shareholding | E128: =SUM(E126:E127) -> 0.85 | F128: =SUM(F126:F127) -> 0.15 | G128: =SUM(G126:G127) -> 0 | H128: =SUM(E128:G128) -> 1
B130: Development Returns ($000s) | E130: Hāpai | F130: KPV | G130: Vendor | H130: Total
...

Sheet House Build Up
A1: Design | C1: 3500
A2: Consenting | C2: 10000
A3: Laterals/ drainage | C3: 15000
A4: House | B4: 3000 | C4: =B4*122 -> 366000
C5: =C4+C3+C2+C1 -> 394500
B6: 122 | C6: =C5/B6 -> 3233.6066
B7: GST | C7: =C6*15% -> 485.04098
C8: =C7+C6 -> 3718.6475

Sheet For Slides - Freehold
B2: Formula Driven: | L2: Formula Driven:
C4: Freehold | F4: Leasehold | I4: Variance | M4: 25% Vendor Share | R4: 50% Vendor Share
C6: A Class | D6: B Class | F6: A Class | G6: B Class | I6: A Class | J6: B Class | M6: Hāpai | N6: KPV | O6: Vendor | P6: Total | R6: Hāpai | S6: KPV | T6: Vendor | U6: Total
B7: Shareholdings | L7: Shareholdings
B8: A-Class | C8: =Output!J62 -> 0.7 | D8: =Output!K62 -> 0 | F8: =Output!J62 -> 0.7 | G8: =Output!K62 -> 0 | I8: =C8-F8 -> 0 | J8: =D8-G8 -> 0 | L8: A-Class | M8: =Output!E62 -> 0.7 | N8: =Output!F62 -> 0 | O8: =Output!G62 -> 0 | P8: =Output!H62 -> 0.7 | R8: =Output!E62 -> 0.7 | S8: =Output!F62 -> 0 | T8: =Output!G62 -> 0 | U8: =Output!H62 -> 0.7
B9: B-Class | C9: =Output!J63 -> 0 | D9: =Output!K63 -> 0.3 | F9: =Output!J63 -> 0 | G9: =Output!K63 -> 0.3 | I9: =C9-F9 -> 0 | J9: =D9-G9 -> 0 | L9: B-Class | M9: =Output!E63 -> 0.15 | N9: =Output!F63 -> 0.15 | O9: =Output!G63 -> 0 | P9: =Output!H63 -> 0.3 | R9: =Output!E63 -> 0.15 | S9: =Output!F63 -> 0.15 | T9: =Output!G63 -> 0 | U9: =Output!H63 -> 0.3
B10: Total | C10: =Output!J64 -> 0.7 | D10: =Output!K64 -> 0.3 | F10: =Output!J64 -> 0.7 | G10: =Output!K64 -> 0.3 | I10: =C10-F10 -> 0 | J10: =D10-G10 -> 0 | L10: Total | M10: =Output!E64 -> 0.85 | N10: =Output!F64 -> 0.15 | O10: =Output!G64 -> 0 | P10: =Output!H64 -> 1 | R10: =Output!E64 -> 0.85 | S10: =Output!F64 -> 0.15 | T10: =Output!G64 -> 0 | U10: =Output!H64 -> 1
B12: Development Output | L12: Development Output
B13: Peak Capital (net of preferred) | C13: =Output!J67 -> 20603.539 | D13: =Output!K67 -> 0 | F13: =Output!J67 -> 20603.539 | G13: =Output!K67 -> 0 | I13: =C13-F13 -> 0 | J13: =D13-G13 -> 0 | L13: Peak Capital (net of preferred) | M13: =Output!E67 -> 20603.539 | N13: =Output!F67 -> 0 | O13: =Output!G67 -> 0 | P13: =Output!H67 -> 20603.539 | R13: =Output!E67 -> 20603.539 | S13: =Output!F67 -> 0 | T13: =Output!G67 -> 0 | U13: =Output!H67 -> 20603.539
B15: Share of ORA Surplus | C15: =Output!J69 -> 12588.648 | D15: =Output!K69 -> 5395.1348 | F15: =Output!J69 -> 12588.648 | G15: =Output!K69 -> 5395.1348 | I15: =C15-F15 -> 0 | J15: =D15-G15 -> 0 | L15: Share of ORA Surplus | M15: =Output!E69 -> 15286.215 | N15: =Output!F69 -> 2697.5674 | O15: =Output!G69 -> 0 | P15: =Output!H69 -> 17983.783 | R15: =Output!E69 -> 15286.215 | S15: =Output!F69 -> 2697.5674 | T15: =Output!G69 -> 0 | U15: =Output!H69 -> 17983.783
B16: Share of Preferred Interest | C16: =Output!J70 -> 5250.6435 | D16: =Output!K70 -> 0 | F16: =Output!J70 -> 5250.6435 | G16: =Output!K70 -> 0 | I16: =C16-F16 -> 0 | J16: =D16-G16 -> 0 | L16: Share of Preferred Interest | M16: =Output!E70 -> 5250.6435 | N16: =Output!F70 -> 0 | O16: =Output!G70 -> 0 | P16: =Output!H70 -> 5250.6435 | R16: =Output!E70 -> 5250.6435 | S16: =Output!F70 -> 0 | T16: =Output!G70 -> 0 | U16: =Output!H70 -> 5250.6435
B17: Total | C17: =Output!J71 -> 17839.291 | D17: =Output!K71 -> 5395.1348 | F17: =Output!J71 -> 17839.291 | G17: =Output!K71 -> 5395.1348 | I17: =C17-F17 -> 0 | J17: =D17-G17 -> 0 | L17: Total | M17: =Output!E71 -> 20536.859 | N17: =Output!F71 -> 2697.5674 | O17: =Output!G71 -> 0 | P17: =Output!H71 -> 23234.426 | R17: =Output!E71 -> 20536.859 | S17: =Output!F71 -> 2697.5674 | T17: =Output!G71 -> 0 | U17: =Output!H71 -> 23234.426
B19: Margin (on share of costs) | C19: =Output!J73 -> 0.20597017 | D19: =Output!K73 -> n/a | F19: =Output!J73 -> 0.20597017 | G19: =Output!K73 -> n/a | I19: =C19-F19 -> 0 | J19: - | L19: Margin (on share of costs) | M19: =Output!E73 -> 0.23711593 | N19: =Output!F73 -> n/a | O19: =Output!G73 -> n/a | P19: =Output!H73 -> 0.2682617 | R19: =Output!E73 -> 0.23711593 | S19: =Output!F73 -> n/a | T19: =Output!G73 -> n/a | U19: =Output!H73 -> 0.2682617
B20: Margin (on share of capital) | C20: =Output!J74 -> 0.86583625 | D20: =Output!K74 -> n/a | F20: =Output!J74 -> 0.86583625 | G20: =Output!K74 -> n/a | I20: =C20-F20 -> 0 | J20: - | L20: Margin (on share of capital) | M20: =Output!E74 -> 0.99676362 | N20: =Output!F74 -> n/a | O20: =Output!G74 -> n/a | P20: =Output!H74 -> 1.127691 | R20: =Output!E74 -> 0.99676362 | S20: =Output!F74 -> n/a | T20: =Output!G74 -> n/a | U20: =Output!H74 -> 1.127691
B23: Long Term Investment | L23: Long Term Investment
B24: IRR (15 year - real basis) | C24: =Output!J78 -> 0.18860542 | D24: =Output!K78 -> 2.9802322e-09 | F24: =Output!J78 -> 0.18860542 | G24: =Output!K78 -> 2.9802322e-09 | I24: =C24-F24 -> 0 | J24: =D24-G24 -> 0 | L24: IRR (15 year - real basis) | M24: =Output!E78 -> 0.20309383 | N24: =Output!F78 -> n/a | O24: =Output!G78 -> n/a | P24: =Output!H78 -> 0.21641291 | R24: =Output!E78 -> 0.20309383 | S24: =Output!F78 -> n/a | T24: =Output!G78 -> n/a | U24: =Output!H78 -> 0.21641291
B26: Annual Cashflow (at maturity) | C26: =Output!J80 -> 2112.4824 | D26: =Output!K80 -> 905.34962 | F26: =Output!J80 -> 2112.4824 | G26: =Output!K80 -> 905.34962 | I26: =C26-F26 -> 0 | J26: =D26-G26 -> 0 | L26: Annual Cashflow (at maturity) | M26: =Output!E80 -> 2565.1573 | N26: =Output!F80 -> 452.67481 | O26: =Output!G80 -> 0 | P26: =Output!H80 -> 3017.8321 | R26: =Output!E80 -> 2565.1573 | S26: =Output!F80 -> 452.67481 | T26: =Output!G80 -> 0 | U26: =Output!H80 -> 3017.8321
B28: Investment Value (at maturity) | C28: =Output!J82 -> 12071.328 | D28: =Output!K82 -> 5173.4264 | F28: =Output!J82 -> 12071.328 | G28: =Output!K82 -> 5173.4264 | I28: =C28-F28 -> 0 | J28: =D28-G28 -> 0 | L28: Investment Value (at maturity) | M28: =Output!E82 -> 14658.041 | N28: =Output!F82 -> 2586.7132 | O28: =Output!G82 -> 0 | P28: =Output!H82 -> 17244.755 | R28: =Output!E82 -> 14658.041 | S28: =Output!F82 -> 2586.7132 | T28: =Output!G82 -> 0 | U28: =Output!H82 -> 17244.755
B30: Copy and Paste: | L30: Copy and Paste:
C32: Freehold | F32: Leasehold | I32: Variance | M32: 25% Vendor Share | R32: 50% Vendor Share
C34: A Class | D34: B Class | F34: A Class | G34: B Class | I34: A Class | J34: B Class | M34: Hāpai | N34: KPV | O34: Vendor | P34: Total | R34: Hāpai | S34: KPV | T34: Vendor | U34: Total
B35: Shareholdings | L35: Shareholdings
B36: A-Class | C36: 0.7 | D36: 0 | F36: 0.7 | G36: 0 | I36: =C36-F36 -> 0 | J36: =D36-G36 -> 0 | L36: A-Class | M36: 0.525 | N36: 0 | O36: 0.175 | P36: 0.7 | R36: 0.35 | S36: 0 | T36: 0.35 | U36: 0.7
B37: B-Class | C37: 0 | D37: 0.3 | F37: 0 | G37: 0.3 | I37: =C37-F37 -> 0 | J37: =D37-G37 -> 0 | L37: B-Class | M37: 0.15 | N37: 0.15 | O37: 0 | P37: 0.3 | R37: 0.15 | S37: 0.15 | T37: 0 | U37: 0.3
B38: Total | C38: 0.7 | D38: 0.3 | F38: 0.7 | G38: 0.3 | I38: =C38-F38 -> 0 | J38: =D38-G38 -> 0 | L38: Total | M38: 0.675 | N38: 0.15 | O38: 0.175 | P38: 1 | R38: 0.5 | S38: 0.15 | T38: 0.35 | U38: 1
B40: Development Output | L40: Development Output
B41: Peak Capital (net of preferred) | C41: 31858.35 | D41: 0 | F41: 17103.852 | G41: 0 | I41: =C41-F41 -> 14754.498 | J41: =D41-G41 -> 0 | L41: Peak Capital (net of preferred) | M41: 23893.763 | N41: 0 | O41: 7964.5875 | P41: 31858.35 | R41: 15929.175 | S41: 0 | T41: 15929.175 | U41: 31858.35
B43: Share of ORA Surplus | C43: 10535.836 | D43: 4515.3583 | F43: 23286.532 | G43: 9979.9423 | I43: =C43-F43 -> -12750.696 | J43: =D43-G43 -> -5464.584 | L43: Share of ORA Surplus | M43: 10159.556 | N43: 2257.6792 | O43: 2633.959 | P43: 15051.194 | R43: 7525.5972 | S43: 2257.6792 | T43: 5267.9181 | U43: 15051.194
B44: Share of Preferred Interest | C44: 11251.331 | D44: 0 | F44: 3794.605 | G44: 0 | I44: =C44-F44 -> 7456.7257 | J44: =D44-G44 -> 0 | L44: Share of Preferred Interest | M44: 8438.498 | N44: 0 | O44: 2812.8327 | P44: 11251.331 | R44: 5625.6654 | S44: 0 | T44: 5625.6654 | U44: 11251.331
B45: Total | C45: 21787.167 | D45: 4515.3583 | F45: 27081.137 | G45: 9979.9423 | I45: =C45-F45 -> -5293.9702 | J45: =D45-G45 -> -5464.584 | L45: Total | M45: 18598.054 | N45: 2257.6792 | O45: 5446.7917 | P45: 26302.525 | R45: 13151.263 | S45: 2257.6792 | T45: 10893.583 | U45: 26302.525
B47: Margin (on share of costs) | C47: 0.19722253 | D47: n/a | F47: 0.27159516 | G47: n/a | I47: =C47-F47 -> -0.074372624 | J47: - | L47: Margin (on share of costs) | M47: 0.22447192 | N47: n/a | O47: 0.19722253 | P47: 0.23809661 | R47: 0.23809661 | S47: n/a | T47: 0.19722253 | U47: 0.23809661
B48: Margin (on share of capital) | C48: 0.68387618 | D48: n/a | F48: 1.5833356 | G48: n/a | I48: =C48-F48 -> -0.89945939 | J48: - | L48: Margin (on share of capital) | M48: 0.7783644 | N48: n/a | O48: 0.68387618 | P48: 0.82560851 | R48: 0.82560851 | S48: n/a | T48: 0.68387618 | U48: 0.82560851
B51: Long Term Investment | L51: Long Term Investment
B52: IRR (15 year - real basis) | C52: 0.15064594 | D52: 2.9802322e-09 | F52: 0.28837599 | G52: 2.9802322e-09 | I52: =C52-F52 -> -0.13773005 | J52: =D52-G52 -> 0 | L52: IRR (15 year - real basis) | M52: 0.16317164 | N52: n/a | O52: 0.15064594 | P52: 0.1688893 | R52: 0.1688893 | S52: n/a | T52: 0.15064594 | U52: 0.1688893
B54: Annual Cashflow (at maturity) | C54: 2062.8409 | D54: 884.07469 | F54: 1123.9138 | G54: 481.67735 | I54: =C54-F54 -> 938.92711 | J54: =D54-G54 -> 402.39733 | L54: Annual Cashflow (at maturity) | M54: 1989.168 | N54: 442.03734 | O54: 515.71023 | P54: 2946.9156 | R54: 1473.4578 | S54: 442.03734 | T54: 1031.4205 | U54: 2946.9156
B56: Investment Value (at maturity) | C56: 11787.662 | D56: 5051.8554 | F56: 6422.3647 | G56: 2752.442 | I56: =C56-F56 -> 5365.2978 | J56: =D56-G56 -> 2299.4133 | L56: Investment Value (at maturity) | M56: 11366.675 | N56: 2525.9277 | O56: 2946.9156 | P56: 16839.518 | R56: 8419.7589 | S56: 2525.9277 | T56: 5893.8312 | U56: 16839.518

Sheet For Slides - Ground Lease
B2: Formula Driven: | L2: Formula Driven:
C4: Freehold | F4: Leasehold | I4: Variance | M4: 25% Vendor Share | R4: 50% Vendor Share
C6: A Class | D6: B Class | F6: A Class | G6: B Class | I6: A Class | J6: B Class | M6: Hāpai | N6: KPV | O6: Vendor | P6: Total | R6: Hāpai | S6: KPV | T6: Vendor | U6: Total
B7: Shareholdings | L7: Shareholdings
B8: A-Class | C8: =Output!J62 -> 0.7 | D8: =Output!K62 -> 0 | F8: =Output!J62 -> 0.7 | G8: =Output!K62 -> 0 | I8: =C8-F8 -> 0 | J8: =D8-G8 -> 0 | L8: A-Class | M8: =Output!E62 -> 0.7 | N8: =Output!F62 -> 0 | O8: =Output!G62 -> 0 | P8: =Output!H62 -> 0.7 | R8: =Output!E62 -> 0.7 | S8: =Output!F62 -> 0 | T8: =Output!G62 -> 0 | U8: =Output!H62 -> 0.7
B9: B-Class | C9: =Output!J63 -> 0 | D9: =Output!K63 -> 0.3 | F9: =Output!J63 -> 0 | G9: =Output!K63 -> 0.3 | I9: =C9-F9 -> 0 | J9: =D9-G9 -> 0 | L9: B-Class | M9: =Output!E63 -> 0.15 | N9: =Output!F63 -> 0.15 | O9: =Output!G63 -> 0 | P9: =Output!H63 -> 0.3 | R9: =Output!E63 -> 0.15 | S9: =Output!F63 -> 0.15 | T9: =Output!G63 -> 0 | U9: =Output!H63 -> 0.3
B10: Total | C10: =Output!J64 -> 0.7 | D10: =Output!K64 -> 0.3 | F10: =Output!J64 -> 0.7 | G10: =Output!K64 -> 0.3 | I10: =C10-F10 -> 0 | J10: =D10-G10 -> 0 | L10: Total | M10: =Output!E64 -> 0.85 | N10: =Output!F64 -> 0.15 | O10: =Output!G64 -> 0 | P10: =Output!H64 -> 1 | R10: =Output!E64 -> 0.85 | S10: =Output!F64 -> 0.15 | T10: =Output!G64 -> 0 | U10: =Output!H64 -> 1
B12: Development Output | L12: Development Output
B13: Peak Capital (net of preferred) | C13: =Output!J67 -> 20603.539 | D13: =Output!K67 -> 0 | F13: =Output!J67 -> 20603.539 | G13: =Output!K67 -> 0 | I13: =C13-F13 -> 0 | J13: =D13-G13 -> 0 | L13: Peak Capital (net of preferred) | M13: =Output!E67 -> 20603.539 | N13: =Output!F67 -> 0 | O13: =Output!G67 -> 0 | P13: =Output!H67 -> 20603.539 | R13: =Output!E67 -> 20603.539 | S13: =Output!F67 -> 0 | T13: =Output!G67 -> 0 | U13: =Output!H67 -> 20603.539
B15: Share of ORA Surplus | C15: =Output!J69 -> 12588.648 | D15: =Output!K69 -> 5395.1348 | F15: =Output!J69 -> 12588.648 | G15: =Output!K69 -> 5395.1348 | I15: =C15-F15 -> 0 | J15: =D15-G15 -> 0 | L15: Share of ORA Surplus | M15: =Output!E69 -> 15286.215 | N15: =Output!F69 -> 2697.5674 | O15: =Output!G69 -> 0 | P15: =Output!H69 -> 17983.783 | R15: =Output!E69 -> 15286.215 | S15: =Output!F69 -> 2697.5674 | T15: =Output!G69 -> 0 | U15: =Output!H69 -> 17983.783
B16: Share of Preferred Interest | C16: =Output!J70 -> 5250.6435 | D16: =Output!K70 -> 0 | F16: =Output!J70 -> 5250.6435 | G16: =Output!K70 -> 0 | I16: =C16-F16 -> 0 | J16: =D16-G16 -> 0 | L16: Share of Preferred Interest | M16: =Output!E70 -> 5250.6435 | N16: =Output!F70 -> 0 | O16: =Output!G70 -> 0 | P16: =Output!H70 -> 5250.6435 | R16: =Output!E70 -> 5250.6435 | S16: =Output!F70 -> 0 | T16: =Output!G70 -> 0 | U16: =Output!H70 -> 5250.6435
B17: Total | C17: =Output!J71 -> 17839.291 | D17: =Output!K71 -> 5395.1348 | F17: =Output!J71 -> 17839.291 | G17: =Output!K71 -> 5395.1348 | I17: =C17-F17 -> 0 | J17: =D17-G17 -> 0 | L17: Total | M17: =Output!E71 -> 20536.859 | N17: =Output!F71 -> 2697.5674 | O17: =Output!G71 -> 0 | P17: =Output!H71 -> 23234.426 | R17: =Output!E71 -> 20536.859 | S17: =Output!F71 -> 2697.5674 | T17: =Output!G71 -> 0 | U17: =Output!H71 -> 23234.426
B19: Margin (on share of costs) | C19: =Output!J73 -> 0.20597017 | D19: =Output!K73 -> n/a | F19: =Output!J73 -> 0.20597017 | G19: =Output!K73 -> n/a | I19: =C19-F19 -> 0 | J19: - | L19: Margin (on share of costs) | M19: =Output!E73 -> 0.23711593 | N19: =Output!F73 -> n/a | O19: =Output!G73 -> n/a | P19: =Output!H73 -> 0.2682617 | R19: =Output!E73 -> 0.23711593 | S19: =Output!F73 -> n/a | T19: =Output!G73 -> n/a | U19: =Output!H73 -> 0.2682617
B20: Margin (on share of capital) | C20: =Output!J74 -> 0.86583625 | D20: =Output!K74 -> n/a | F20: =Output!J74 -> 0.86583625 | G20: =Output!K74 -> n/a | I20: =C20-F20 -> 0 | J20: - | L20: Margin (on share of capital) | M20: =Output!E74 -> 0.99676362 | N20: =Output!F74 -> n/a | O20: =Output!G74 -> n/a | P20: =Output!H74 -> 1.127691 | R20: =Output!E74 -> 0.99676362 | S20: =Output!F74 -> n/a | T20: =Output!G74 -> n/a | U20: =Output!H74 -> 1.127691
B23: Long Term Investment | L23: Long Term Investment
B24: IRR (15 year - real basis) | C24: =Output!J78 -> 0.18860542 | D24: =Output!K78 -> 2.9802322e-09 | F24: =Output!J78 -> 0.18860542 | G24: =Output!K78 -> 2.9802322e-09 | I24: =C24-F24 -> 0 | J24: =D24-G24 -> 0 | L24: IRR (15 year - real basis) | M24: =Output!E78 -> 0.20309383 | N24: =Output!F78 -> n/a | O24: =Output!G78 -> n/a | P24: =Output!H78 -> 0.21641291 | R24: =Output!E78 -> 0.20309383 | S24: =Output!F78 -> n/a | T24: =Output!G78 -> n/a | U24: =Output!H78 -> 0.21641291
B26: Annual Cashflow (at maturity) | C26: =Output!J80 -> 2112.4824 | D26: =Output!K80 -> 905.34962 | F26: =Output!J80 -> 2112.4824 | G26: =Output!K80 -> 905.34962 | I26: =C26-F26 -> 0 | J26: =D26-G26 -> 0 | L26: Annual Cashflow (at maturity) | M26: =Output!E80 -> 2565.1573 | N26: =Output!F80 -> 452.67481 | O26: =Output!G80 -> 0 | P26: =Output!H80 -> 3017.8321 | R26: =Output!E80 -> 2565.1573 | S26: =Output!F80 -> 452.67481 | T26: =Output!G80 -> 0 | U26: =Output!H80 -> 3017.8321
B28: Investment Value (at maturity) | C28: =Output!J82 -> 12071.328 | D28: =Output!K82 -> 5173.4264 | F28: =Output!J82 -> 12071.328 | G28: =Output!K82 -> 5173.4264 | I28: =C28-F28 -> 0 | J28: =D28-G28 -> 0 | L28: Investment Value (at maturity) | M28: =Output!E82 -> 14658.041 | N28: =Output!F82 -> 2586.7132 | O28: =Output!G82 -> 0 | P28: =Output!H82 -> 17244.755 | R28: =Output!E82 -> 14658.041 | S28: =Output!F82 -> 2586.7132 | T28: =Output!G82 -> 0 | U28: =Output!H82 -> 17244.755
B30: Copy and Paste: | L30: Copy and Paste:
C32: Freehold | F32: Leasehold | I32: Variance | M32: 25% Vendor Share | R32: 50% Vendor Share
C34: A Class | D34: B Class | F34: A Class | G34: B Class | I34: A Class | J34: B Class | M34: Hāpai | N34: KPV | O34: Vendor | P34: Total | R34: Hāpai | S34: KPV | T34: Vendor | U34: Total
B35: Shareholdings | L35: Shareholdings
B36: A-Class | C36: 0.7 | D36: 0 | F36: 0.7 | G36: 0 | I36: =C36-F36 -> 0 | J36: =D36-G36 -> 0 | L36: A-Class | M36: 0.525 | N36: 0 | O36: 0.175 | P36: 0.7 | R36: 0.35 | S36: 0 | T36: 0.35 | U36: 0.7
B37: B-Class | C37: 0.15 | D37: 0.3 | F37: 0.15 | G37: 0.3 | I37: =C37-F37 -> 0 | J37: =D37-G37 -> 0 | L37: B-Class | M37: 0.15 | N37: 0.15 | O37: 0 | P37: 0.3 | R37: 0.15 | S37: 0.15 | T37: 0 | U37: 0.3
B38: Total | C38: 0.7 | D38: 0.3 | F38: 0.7 | G38: 0.3 | I38: =C38-F38 -> 0 | J38: =D38-G38 -> 0 | L38: Total | M38: 0.675 | N38: 0.15 | O38: 0.175 | P38: 1 | R38: 0.5 | S38: 0.15 | T38: 0.35 | U38: 1
B40: Development Output | L40: Development Output
B41: Peak Capital (net of preferred) | C41: 31858.35 | D41: 0 | F41: 17103.852 | G41: 0 | I41: =C41-F41 -> 14754.498 | J41: =D41-G41 -> 0 | L41: Peak Capital (net of preferred) | M41: 12827.889 | N41: 0 | O41: 4275.963 | P41: 17103.852 | R41: 8551.9259 | S41: 0 | T41: 8551.9259 | U41: 17103.852
B43: Share of ORA Surplus | C43: 10535.836 | D43: 4515.3583 | F43: 23286.532 | G43: 9979.9423 | I43: =C43-F43 -> -12750.696 | J43: =D43-G43 -> -5464.584 | L43: Share of ORA Surplus | M43: 22454.87 | N43: 4989.9711 | O43: 5821.633 | P43: 33266.474 | R43: 16633.237 | S43: 4989.9711 | T43: 11643.266 | U43: 33266.474
B44: Share of Preferred Interest | C44: 11251.331 | D44: 0 | F44: 3794.605 | G44: 0 | I44: =C44-F44 -> 7456.7257 | J44: =D44-G44 -> 0 | L44: Share of Preferred Interest | M44: 2845.9538 | N44: 0 | O44: 948.65126 | P44: 3794.605 | R44: 1897.3025 | S44: 0 | T44: 1897.3025 | U44: 3794.605
B45: Total | C45: 21787.167 | D45: 4515.3583 | F45: 27081.137 | G45: 9979.9423 | I45: =C45-F45 -> -5293.9702 | J45: =D45-G45 -> -5464.584 | L45: Total | M45: 25300.824 | N45: 4989.9711 | O45: 6770.2843 | P45: 37061.079 | R45: 18530.54 | S45: 4989.9711 | T45: 13540.569 | U45: 37061.079
B47: Margin (on share of costs) | C47: 0.19722253 | D47: n/a | F47: 0.27159516 | G47: n/a | I47: =C47-F47 -> -0.074372624 | J47: - | L47: Margin (on share of costs) | M47: 0.33832067 | N47: n/a | O47: 0.27159516 | P47: 0.37168342 | R47: 0.37168342 | S47: n/a | T47: 0.27159516 | U47: 0.37168342
B48: Margin (on share of capital) | C48: 0.68387618 | D48: n/a | F48: 1.5833356 | G48: n/a | I48: =C48-F48 -> -0.89945939 | J48: - | L48: Margin (on share of capital) | M48: 1.9723295 | N48: n/a | O48: 1.5833356 | P48: 2.1668265 | R48: 2.1668265 | S48: n/a | T48: 1.5833356 | U48: 2.1668265
B51: Long Term Investment | L51: Long Term Investment
B52: IRR (15 year - real basis) | C52: 0.15846584 | D52: 2.9802322e-09 | F52: 0.28743779 | G52: 2.9802322e-09 | I52: =C52-F52 -> -0.12897195 | J52: =D52-G52 -> 0 | L52: IRR (15 year - real basis) | M52: 0.32388808 | N52: n/a | O52: 0.28837599 | P52: 0.34009762 | R52: 0.34009762 | S52: n/a | T52: 0.28837599 | U52: 0.34009762
B54: Annual Cashflow (at maturity) | C54: 2062.8409 | D54: 884.07469 | F54: 1123.9138 | G54: 481.67735 | I54: =C54-F54 -> 938.92711 | J54: =D54-G54 -> 402.39733 | L54: Annual Cashflow (at maturity) | M54: 1083.774 | N54: 240.83868 | O54: 280.97846 | P54: 1605.5912 | R54: 802.79559 | S54: 240.83868 | T54: 561.95691 | U54: 1605.5912
B56: Investment Value (at maturity) | C56: 20628.409 | D56: 8840.7469 | F56: 4979.6241 | G56: 2134.1246 | I56: =C56-F56 -> 15648.785 | J56: =D56-G56 -> 6706.6222 | L56: Investment Value (at maturity) | M56: 6192.9945 | N56: 1376.221 | O56: 1605.5912 | P56: 9174.8067 | R56: 4587.4034 | S56: 1376.221 | T56: 3211.1823 | U56: 9174.8067
